mitchell/LM/mitchell.v
module Barrel8L(
    input [7:0] data_i,
    input [2:0] shift_i,
    output reg [7:0] data_o
    );	 
 
   always @*
      case (shift_i)
         3'd0: data_o = data_i;
         3'd1: data_o = data_i << 1;
         3'd2: data_o = data_i << 2;
         3'd3: data_o = data_i << 3;
         3'd4: data_o = data_i << 4;
         3'd5: data_o = data_i << 5;
         3'd6: data_o = data_i << 6;
         3'd7: data_o = data_i << 7;
      endcase

endmodule


module Barrel8R (
    input [7:0] data_i,
	input [2:0] shift_i,
	output reg [7:0] data_o
    );

	always @*
      case (shift_i)
         3'd0: data_o = data_i;
         3'd1: data_o = data_i >> 1;
         3'd2: data_o = data_i >> 2;
         3'd3: data_o = data_i >> 3;
         3'd4: data_o = data_i >> 4;
         3'd5: data_o = data_i >> 5;
         3'd6: data_o = data_i >> 6;
         3'd7: data_o = data_i >> 7;
      endcase
endmodule


module Barrel16L(
    input [15:0] data_i,
    input [3:0] shift_i,
    output reg [15:0] data_o
    );	 
 
   always @*
      case (shift_i)
         4'd0: data_o = data_i;
         4'd1: data_o = data_i << 1;
         4'd2: data_o = data_i << 2;
         4'd3: data_o = data_i << 3;
         4'd4: data_o = data_i << 4;
         4'd5: data_o = data_i << 5;
         4'd6: data_o = data_i << 6;
         4'd7: data_o = data_i << 7;
         4'd8: data_o = data_i<<8;
         4'd9: data_o = data_i << 9;
         4'd10: data_o = data_i << 10;
         4'd11: data_o = data_i << 11;
         4'd12: data_o = data_i << 12;
         4'd13: data_o = data_i << 13;
         4'd14: data_o = data_i << 14;
         4'd15: data_o = data_i << 15;
      endcase

endmodule


module carry_lookahead_inc(
    input [2:0] i_add1,
    output [3:0] o_result
);
    
    wire [2:0] carry;
    wire [2:0] sum;
    
    // Generate carry signals using lookahead logic
    assign carry[0] = 1'b1; // Incrementing, so initial carry-in is 1
    assign carry[1] = (i_add1[0] & carry[0]);
    assign carry[2] = (i_add1[1] & carry[1]);
    
    // Compute sum bits
    assign sum[0] = i_add1[0] ^ carry[0];
    assign sum[1] = i_add1[1] ^ carry[1];
    assign sum[2] = i_add1[2] ^ carry[2];

    // Output the incremented result
    assign o_result = {carry[2],sum};
    
endmodule


module AntiLog(
    input  [10:0] data_i,   // [10] = lr flag, [9:7] = exponent, [6:0] = fraction
    output [15:0] data_o    // 16-bit approximate product output
);

    // -------------------------------
    // Left Barrel Shift Branch (for lr = 1)
    // -------------------------------
    wire [15:0] l1_in;
    assign l1_in = {8'b0, 1'b1, data_i[6:0]};  // 8 + 1 + 7 = 16 bits

    wire [2:0] k_enc;
    wire [3:0] k_enc_inc;
    assign k_enc = {1'b0,data_i[9:7]};  // Extract exponent
    // assign k_enc_inc = k_enc + 3'b001;  // Simple increment

    carry_lookahead_inc inc(
        .i_add1(k_enc),
        .o_result(k_enc_inc)
    );

    wire [15:0] l1_out;
    Barrel16L L1shift (
        .data_i(l1_in),
        .shift_i(k_enc_inc),
        .data_o(l1_out)
    );

    // -------------------------------
    // Right Barrel Shift Branch (for lr = 0)
    // -------------------------------
    wire [7:0] r_in;
    assign r_in = {1'b1, data_i[6:0]};  // 1 + 7 = 8 bits

    wire [2:0] enc;
    assign enc = ~data_i[9:7];  // Compute correct right-shift amount

    wire [7:0] r_out;
    Barrel8R Rshift (
        .data_i(r_in),
        .shift_i(enc),
        .data_o(r_out)
    );
    
    assign data_o = data_i[10] ? l1_out : {8'd0, r_out};  // Full selection

endmodule


module PEncoder (
    input [7:0] A,
    output [2:0] out
);

    wire temp1, temp2, temp3, temp4, temp5;

    assign temp1 = A[1] || A[3];
    assign temp2 = A[2] || A[3];
    assign temp3 = A[4] || A[5];
    assign temp4 = A[6] || A[7];
    assign temp5 = A[5] || A[7];

    assign out[0] = temp1 || temp5;
    assign out[1] = temp2 || temp4;
    assign out[2] = temp3 || temp4;
    
endmodule


module Muxes2in1Array4(
    input [3:0] data_i,
    input select_i,
    output [3:0] data_o
    );

    assign data_o = select_i ? data_i : 4'b0000;

endmodule


module LOD4(
    input [3:0] data_i,
    output [3:0] data_o
    ); 
    wire mux0;
    wire mux1;
    wire mux2;
    
    assign mux2 = data_i[3] ? 1'b0 : 1'b1;
    assign mux1 = data_i[2] ? 1'b0 : mux2;
    assign mux0 = data_i[1] ? 1'b0 : mux1;
    
    assign data_o[3] = data_i[3];
    assign data_o[2] = (mux2 & data_i[2]);
    assign data_o[1] = (mux1 & data_i[1]);
    assign data_o[0] = (mux0 & data_i[0]);
endmodule


module LOD2(
    input [1:0] data_i,
    output [1:0] data_o
    ); 
    wire mux0;

    assign mux0 = data_i[1] ? 1'b0 : 1'b1;

    assign data_o[1] = data_i[1];
    assign data_o[0] = (mux0 & data_i[0]);
endmodule


module LOD(
    input [7:0] A,
    output zero_o,
    output [7:0] O
    );

    wire [7:0] z;
    wire [1:0] select;
    wire [1:0] zdet;

    LOD4 lod4_1 (
        .data_i(A[7:4]), 
        .data_o(z[7:4])
    );

    LOD4 lod4_0 (
        .data_i(A[3:0]), 
        .data_o(z[3:0])
    );

    LOD2 lod4_middle (
        .data_i( zdet),  // Expand zdet to 4-bit
        .data_o(select) // Expand select to match 4-bit output
    );

    assign zdet[1] = A[7] | A[6] | A[5] | A[4];
    assign zdet[0] = A[3] | A[2] | A[1] | A[0];
    assign zero_o = ~(zdet[1] | zdet[0]);

    Muxes2in1Array4 Inst_MUX214_1 (
        .data_i(z[7:4]), 
        .select_i(select[1]), 
        .data_o(O[7:4])
    );

    Muxes2in1Array4 Inst_MUX214_0 (
        .data_i(z[3:0]), 
        .select_i(select[0]), 
        .data_o(O[3:0])
    );

endmodule


module MITCHEL(
    input [8:0] x,
    input [8:0] y,
    output [16:0] p

    // output [7:0] A,B,
    // output [7:0] LODa,LODb,
    // output [2:0] kA, kB,   // Expose kA and kB
    // output [10:0] op1, op2, L,  // Expose internal values
    // output [15:0] tmp_out 
    );

    wire [7:0] A,B;
    assign A=x[7:0];
    assign B=y[7:0];

    wire [7:0] LODa,LODb;
    wire [2:0] kA,kB;
    wire zeroA,zeroB;

    LOD lodA(A,zeroA,LODa);
    LOD lodB(B,zeroB,LODb);

    PEncoder peA(LODa,kA);
    PEncoder peB(LODb,kB);

    wire [2:0] kA_inv;
	wire [7:0] barrelA;
	
	assign kA_inv = ~kA;
	
	Barrel8L BShiftA (
		.data_i(A),
		.shift_i(kA_inv),
		.data_o(barrelA)
 	 ); 

    wire [2:0] kB_inv;
	wire [7:0] barrelB;

	assign kB_inv = ~kB;
	
	Barrel8L BShiftB (
		.data_i(B),
		.shift_i(kB_inv),
		.data_o(barrelB)
 	 );

    wire [10:0] op1,op2,L;

    assign op1={1'b0,kA,barrelA[6:0]};
    assign op2={1'b0,kB,barrelB[6:0]};

    assign L=op1+op2;

    wire [15:0] tmp_out; 

	AntiLog anti_log(
		.data_i(L),
		.data_o(tmp_out)
	);
	
	wire prod_sign; 
	wire [15:0] tmp_sign;
	
	assign prod_sign = x[8] ^ y[8];
	assign tmp_sign = {17{prod_sign}} ^ tmp_out;
	
	// is zero 
	wire not_zero;
	assign not_zero = (~zeroA | x[8] | x[0]) & (~zeroB | y[8] | y[0]);
	
	assign p = not_zero ? tmp_sign : 16'b0;

endmodule

mitchell/LM/mitchel_tb.v
`timescale 1ns / 1ps

module MITCHEL_tb;

    // Inputs (8-bit unsigned)
    reg [8:0] x, y;
    
    // Outputs
    wire [16:0] p;
    // wire [7:0] LODa,LODb,A,B;
    // wire [2:0] kA, kB;
    // wire [10:0] op1, op2, L;
    // wire [15:0] tmp_out;

    // Intermediate signals for signed values
    // integer signed_in1, signed_in2, signed_product;

    // Instantiate the ILM module
    MITCHEL uut (
        .x(x), 
        .y(y), 
        .p(p)

        // .A(A),
        // .B(B),
        // .LODa(LODa),
        // .LODb(LODb),
        // .kA(kA), 
        // .kB(kB),
        // .op1(op1),
        // .op2(op2),
        // .L(L),
        // .tmp_out(tmp_out)
    );
    
    // Test cases
    initial begin
        // Enable waveform dumping for GTKWave
        $dumpfile("MITCHEL_tb.vcd");  // Name of the VCD file
        $dumpvars(0, uut);      // Dump all variables in this module

        // Monitor output
        $monitor("Time = %0t | x = %b (%d), y = %b (%d) | Product = %b (%d)", 
                 $time, x,x, y,y , p, p);
        
        // Apply test cases (8-bit unsigned numbers)
                // Test Case 1: 5 * 3
        x = 9'b000000101;  y = 9'b000000011;  #10;
        
        // Test Case 2: 15 * 5
        x = 9'b000001111;  y = 9'b000000101;  #10;
        
        // Test Case 3: 20 * 4
        x = 9'b000010100;  y = 9'b000000100;  #10;
        
        // Test Case 4: 8 * 2
        x = 9'b000001000;  y = 9'b000000010;  #10;
        
        // Test Case 5: 50 * 7
        x = 9'b000110010;  y = 9'b000000111;  #10;
        
        // Test Case 6: 25 * 6
        x = 9'b000011001;  y = 9'b000000110;  #10;
        
        // Test Case 7: 129 * 65
        x = 9'b010000001;  y = 9'b001000001;  #10;
        
        // Test Case 8: 0 * 18
        x = 9'b000000000;  y = 9'b000010010;  #10;
        
        // Test Case 9: 1 * 1
        x = 9'b000000001;  y = 9'b000000001;  #10;
        
        // Test Case 10: 253 * 253
        x = 9'b011111101;  y = 9'b011111101;  #10;



                // Test Case 1: 5 * 3
        x = 9'b100000101;  y = 9'b000000011;  #10;
        
        // Test Case 2: 15 * 5
        x = 9'b000001111;  y = 9'b100000101;  #10;
        
        // Test Case 3: 20 * 4
        x = 9'b100010100;  y = 9'b100000100;  #10;
        
        // Test Case 4: 8 * 2
        x = 9'b100001000;  y = 9'b000000010;  #10;
        
        // Test Case 5: 50 * 7
        x = 9'b000110010;  y = 9'b100000111;  #10;
        
        // Test Case 6: 25 * 6
        x = 9'b100011001;  y = 9'b100000110;  #10;
        
        // Test Case 7: 129 * 65
        x = 9'b110000001;  y = 9'b001000001;  #10;
        
        // Test Case 8: 0 * 18
        x = 9'b000000000;  y = 9'b000010010;  #10;
        
        // Test Case 9: 1 * 1
        x = 9'b000000001;  y = 9'b100000001;  #10;
        
        // Test Case 10: 253 * 253
        x = 9'b111111101;  y = 9'b111111101;  #10;

        // End simulation
        $finish;
    end

    // Always block to update signed values
    // always @(*) begin
    //     signed_in1 = $signed(x);
    //     signed_in2 = $signed(y);
        // signed_product = $signed(p);
    // end
    
endmodule

mitchell/LM/MITCHEL_tb.vcd
$date
	Sun Mar 16 22:07:50 2025
$end
$version
	Icarus Verilog
$end
$timescale
	1ps
$end
$scope module MITCHEL_tb $end
$scope module uut $end
$var wire 3 ! kA_inv [2:0] $end
$var wire 3 " kB_inv [2:0] $end
$var wire 1 # not_zero $end
$var wire 1 $ prod_sign $end
$var wire 9 % x [8:0] $end
$var wire 9 & y [8:0] $end
$var wire 1 ' zeroB $end
$var wire 1 ( zeroA $end
$var wire 16 ) tmp_sign [15:0] $end
$var wire 16 * tmp_out [15:0] $end
$var wire 17 + p [16:0] $end
$var wire 11 , op2 [10:0] $end
$var wire 11 - op1 [10:0] $end
$var wire 3 . kB [2:0] $end
$var wire 3 / kA [2:0] $end
$var wire 8 0 barrelB [7:0] $end
$var wire 8 1 barrelA [7:0] $end
$var wire 8 2 LODb [7:0] $end
$var wire 8 3 LODa [7:0] $end
$var wire 11 4 L [10:0] $end
$var wire 8 5 B [7:0] $end
$var wire 8 6 A [7:0] $end
$scope module BShiftA $end
$var wire 8 7 data_i [7:0] $end
$var wire 3 8 shift_i [2:0] $end
$var reg 8 9 data_o [7:0] $end
$upscope $end
$scope module BShiftB $end
$var wire 8 : data_i [7:0] $end
$var wire 3 ; shift_i [2:0] $end
$var reg 8 < data_o [7:0] $end
$upscope $end
$scope module anti_log $end
$var wire 11 = data_i [10:0] $end
$var wire 3 > enc [2:0] $end
$var wire 8 ? r_out [7:0] $end
$var wire 8 @ r_in [7:0] $end
$var wire 16 A l1_out [15:0] $end
$var wire 16 B l1_in [15:0] $end
$var wire 4 C k_enc_inc [3:0] $end
$var wire 3 D k_enc [2:0] $end
$var wire 16 E data_o [15:0] $end
$scope module L1shift $end
$var wire 16 F data_i [15:0] $end
$var wire 4 G shift_i [3:0] $end
$var reg 16 H data_o [15:0] $end
$upscope $end
$scope module Rshift $end
$var wire 8 I data_i [7:0] $end
$var wire 3 J shift_i [2:0] $end
$var reg 8 K data_o [7:0] $end
$upscope $end
$scope module inc $end
$var wire 3 L i_add1 [2:0] $end
$var wire 3 M sum [2:0] $end
$var wire 4 N o_result [3:0] $end
$var wire 3 O carry [2:0] $end
$upscope $end
$upscope $end
$scope module lodA $end
$var wire 8 P A [7:0] $end
$var wire 1 ( zero_o $end
$var wire 2 Q zdet [1:0] $end
$var wire 8 R z [7:0] $end
$var wire 2 S select [1:0] $end
$var wire 8 T O [7:0] $end
$scope module Inst_MUX214_0 $end
$var wire 4 U data_i [3:0] $end
$var wire 1 V select_i $end
$var wire 4 W data_o [3:0] $end
$upscope $end
$scope module Inst_MUX214_1 $end
$var wire 4 X data_i [3:0] $end
$var wire 1 Y select_i $end
$var wire 4 Z data_o [3:0] $end
$upscope $end
$scope module lod4_0 $end
$var wire 4 [ data_i [3:0] $end
$var wire 1 \ mux2 $end
$var wire 1 ] mux1 $end
$var wire 1 ^ mux0 $end
$var wire 4 _ data_o [3:0] $end
$upscope $end
$scope module lod4_1 $end
$var wire 4 ` data_i [3:0] $end
$var wire 1 a mux2 $end
$var wire 1 b mux1 $end
$var wire 1 c mux0 $end
$var wire 4 d data_o [3:0] $end
$upscope $end
$scope module lod4_middle $end
$var wire 2 e data_i [1:0] $end
$var wire 1 f mux0 $end
$var wire 2 g data_o [1:0] $end
$upscope $end
$upscope $end
$scope module lodB $end
$var wire 8 h A [7:0] $end
$var wire 1 ' zero_o $end
$var wire 2 i zdet [1:0] $end
$var wire 8 j z [7:0] $end
$var wire 2 k select [1:0] $end
$var wire 8 l O [7:0] $end
$scope module Inst_MUX214_0 $end
$var wire 4 m data_i [3:0] $end
$var wire 1 n select_i $end
$var wire 4 o data_o [3:0] $end
$upscope $end
$scope module Inst_MUX214_1 $end
$var wire 4 p data_i [3:0] $end
$var wire 1 q select_i $end
$var wire 4 r data_o [3:0] $end
$upscope $end
$scope module lod4_0 $end
$var wire 4 s data_i [3:0] $end
$var wire 1 t mux2 $end
$var wire 1 u mux1 $end
$var wire 1 v mux0 $end
$var wire 4 w data_o [3:0] $end
$upscope $end
$scope module lod4_1 $end
$var wire 4 x data_i [3:0] $end
$var wire 1 y mux2 $end
$var wire 1 z mux1 $end
$var wire 1 { mux0 $end
$var wire 4 | data_o [3:0] $end
$upscope $end
$scope module lod4_middle $end
$var wire 2 } data_i [1:0] $end
$var wire 1 ~ mux0 $end
$var wire 2 !" data_o [1:0] $end
$upscope $end
$upscope $end
$scope module peA $end
$var wire 8 "" A [7:0] $end
$var wire 1 #" temp1 $end
$var wire 1 $" temp2 $end
$var wire 1 %" temp3 $end
$var wire 1 &" temp4 $end
$var wire 1 '" temp5 $end
$var wire 3 (" out [2:0] $end
$upscope $end
$scope module peB $end
$var wire 8 )" A [7:0] $end
$var wire 1 *" temp1 $end
$var wire 1 +" temp2 $end
$var wire 1 ," temp3 $end
$var wire 1 -" temp4 $end
$var wire 1 ." temp5 $end
$var wire 3 /" out [2:0] $end
$upscope $end
$upscope $end
$upscope $end
$enddefinitions $end
#0
$dumpvars
b1 /"
0."
0-"
0,"
0+"
1*"
b10 )"
b10 ("
0'"
0&"
0%"
1$"
0#"
b100 ""
b1 !"
1~
b1 }
b0 |
1{
1z
1y
b0 x
b10 w
0v
1u
1t
b11 s
b0 r
0q
b0 p
b10 o
1n
b10 m
b10 l
b1 k
b10 j
b1 i
b11 h
b1 g
1f
b1 e
b0 d
1c
1b
1a
b0 `
b100 _
0^
0]
1\
b101 [
b0 Z
0Y
b0 X
b100 W
1V
b100 U
b100 T
b1 S
b100 R
b1 Q
b101 P
b111 O
b1100 N
b100 M
b11 L
b1110 K
b100 J
b11100000 I
b0 H
b1100 G
b11100000 F
b1110 E
b11 D
b1100 C
b11100000 B
b0 A
b11100000 @
b1110 ?
b100 >
b111100000 =
b11000000 <
b110 ;
b11 :
b10100000 9
b101 8
b101 7
b101 6
b11 5
b111100000 4
b100 3
b10 2
b10100000 1
b11000000 0
b10 /
b1 .
b100100000 -
b11000000 ,
b1110 +
b1110 *
b1110 )
0(
0'
b11 &
b101 %
0$
1#
b110 "
b101 !
$end
#10000
b101 "
b101 ;
b100100000 ,
b10 .
b10 /"
b100100000000000 A
b100100000000000 H
b1001000 +
b100 !
b100 8
0*"
1+"
b1001000 )
b11 /
b11 ("
b1 O
b111 C
b111 G
b111 N
b111 M
1#"
b100 2
b100 l
b100 )"
b100 o
b1001000 *
b1001000 E
b100 m
b110 D
b110 L
b1001000 ?
b1001000 K
b1 >
b1 J
b1000 3
b1000 T
b1000 ""
b1000 W
0u
0v
b100 j
b100 w
b10010000 B
b10010000 F
b10010000 @
b10010000 I
0\
b1000 U
b1100010000 4
b1100010000 =
b111110000 -
b1000 R
b1000 _
b10100000 0
b10100000 <
b101 s
b11110000 1
b11110000 9
b1111 [
b101 5
b101 :
b101 h
b1111 6
b1111 7
b1111 P
b101 &
b1111 %
#20000
b1010000 +
b11 !
b11 8
b1010000 )
b100 /
b100 ("
1%"
b1 O
b111 C
b111 G
b111 N
b111 M
0#"
0$"
0V
b1010000 *
b1010000 E
b1 Z
b101000000000000 A
b101000000000000 H
b110 D
b110 L
b1010000 ?
b1010000 K
b1 >
b1 J
b1 X
b10000 3
b10000 T
b10000 ""
b0 W
0f
1Y
b10100000 B
b10100000 F
b10100000 @
b10100000 I
b1 d
1\
b100 U
b10 S
b10 g
b100000000 ,
b1100100000 4
b1100100000 =
b1000100000 -
b10100 R
b100 _
b11 Q
b11 e
b10000000 0
b10000000 <
b100 s
b10100000 1
b10100000 9
b1 `
b100 [
b100 5
b100 :
b100 h
b10100 6
b10100 7
b10100 P
b100 &
b10100 %
#30000
b110 "
b110 ;
1#"
1$"
b100 !
b100 8
1*"
b1 .
b1 /"
b10000 +
b11 /
b11 ("
0+"
b10000 )
b1000 W
0%"
b1 O
b101 C
b101 G
b101 N
b101 M
1V
b10 2
b10 l
b10 )"
b10 o
b10000 *
b10000 E
b1000 3
b1000 T
b1000 ""
b0 Z
b100 D
b100 L
b11 >
b11 J
b10 m
b1000000000000 A
b1000000000000 H
b10000 ?
b10000 K
b0 X
0^
1f
0Y
1u
b10 j
b10 w
b10000000 B
b10000000 F
b10000000 @
b10000000 I
b0 d
0\
0]
b1000 U
b1 S
b1 g
b10000000 ,
b1000000000 4
b1000000000 =
b110000000 -
b1000 R
b1000 _
b1 Q
b1 e
b10000000 0
b10000000 <
b10 s
b10000000 1
b10000000 9
b0 `
b1000 [
b10 5
b10 :
b10 h
b1000 6
b1000 7
b1000 P
b10 &
b1000 %
#40000
b1 C
b1 G
b1 N
b1 M
b101 "
b101 ;
b0 D
b0 L
b111 >
b111 J
0*"
b10 .
b10 /"
b101010000 +
b10 !
b10 8
1+"
b101010000 )
b101 /
b101 ("
1%"
1'"
0#"
0$"
0V
b100 2
b100 l
b100 )"
b100 o
b101010000 *
b101010000 E
b10 Z
b100 m
b101010000 A
b101010000 H
b1 ?
b1 K
b10 X
1]
b100000 3
b100000 T
b100000 ""
b0 W
0f
1Y
0u
b100 j
b100 w
b10101000 B
b10101000 F
b10101000 @
b10101000 I
0c
b10 d
1\
b10 U
b10 S
b10 g
b101100000 ,
b10000101000 4
b10000101000 =
b1011001000 -
b100010 R
b10 _
b11 Q
b11 e
b11100000 0
b11100000 <
b111 s
b11001000 1
b11001000 9
b11 `
b10 [
b111 5
b111 :
b111 h
b110010 6
b110010 7
b110010 P
b111 &
b110010 %
#50000
b111 O
b1000 C
b1000 G
b1000 N
b0 M
b10001000 ?
b10001000 K
b111 D
b111 L
b0 >
b0 J
b11 !
b11 8
b10001000 +
b100 /
b100 ("
b10001000 )
1%"
0'"
b10001000 *
b10001000 E
b10000 3
b10000 T
b10000 ""
b1 Z
b1000100000000000 A
b1000100000000000 H
b1 X
0]
b10001000 B
b10001000 F
b10001000 @
b10001000 I
1c
b1 d
0\
0^
b1000 U
b101000000 ,
b1110001000 4
b1110001000 =
b1001001000 -
b11000 R
b1000 _
b11000000 0
b11000000 <
b110 s
b11001000 1
b11001000 9
b1 `
b1001 [
b110 5
b110 :
b110 h
b11001 6
b11001 7
b11001 P
b110 &
b11001 %
#60000
b1 "
b1 ;
1-"
1&"
1'"
b110 .
b110 /"
0n
b10000011000000 +
b0 !
b0 8
0+"
b100 r
b10000011000000 )
b111 /
b111 ("
0~
1q
b11 O
b110 C
b110 G
b110 N
b110 M
0%"
0V
b1000000 2
b1000000 l
b1000000 )"
b0 o
b10 k
b10 !"
b10000011000000 *
b10000011000000 E
0c
1^
0{
b100 p
1v
b1 m
b11 i
b11 }
b10000011000000 A
b10000011000000 H
b101 D
b101 L
b100000 ?
b100000 K
b10 >
b10 J
0b
b10000000 3
b10000000 T
b10000000 ""
b1000 Z
1]
0f
1Y
0z
b100 |
1u
b1000001 j
b1 w
b10000011 B
b10000011 F
b10000011 @
b10000011 I
0a
b1000 X
1\
b1 U
b10 S
b10 g
b1100000010 ,
b11010000011 4
b11010000011 =
b1110000001 -
b1000 d
b10000001 R
b1 _
b11 Q
b11 e
b10000010 0
b10000010 <
b100 x
b1 s
b10000001 1
b10000001 9
b1000 `
b1 [
b1000001 5
b1000001 :
b1000001 h
b10000001 6
b10000001 7
b10000001 P
b1000001 &
b10000001 %
#70000
b1 O
b101 C
b101 G
b101 N
b101 M
0#
1,"
b11 "
b11 ;
b100 D
b100 L
b11 >
b11 J
b100 .
b100 /"
b0 +
b111 !
b111 8
0-"
b10010 )
b0 /
b0 ("
1(
0&"
0'"
1f
0Y
b10000 2
b10000 l
b10000 )"
b1 r
b10010 *
b10010 E
1c
b0 S
b0 g
1{
b1 p
b10 m
b1001000000000 A
b1001000000000 H
b10010 ?
b10010 K
1b
b0 3
b0 T
b0 ""
b0 Z
b0 U
1z
b1 |
0v
b10010 j
b10 w
b10010000 B
b10010000 F
b10010000 @
b10010000 I
1a
b0 X
b0 _
b1000010000 ,
b11 i
b11 }
b1000010000 4
b1000010000 =
b0 -
b0 R
b0 d
b0 Q
b0 e
b10010000 0
b10010000 <
b1 x
b10 s
b0 1
b0 9
b0 `
b0 [
b10010 5
b10010 :
b10010 h
b0 6
b0 7
b0 P
b10010 &
b0 %
#80000
b1 C
b1 G
b1 N
b1 M
b0 D
b0 L
b111 >
b111 J
b111 "
b111 ;
b0 .
b0 /"
b1 )
b1 o
0,"
1n
b1 3
b1 T
b1 ""
b1 W
b1 *
b1 E
b1 2
b1 l
b1 )"
b0 r
0(
1V
b100000000 A
b100000000 H
b1 ?
b1 K
b0 p
b1 m
1~
0q
b1 U
b1 S
b1 g
b10000000 B
b10000000 F
b10000000 @
b10000000 I
b0 |
1v
b1 j
b1 w
b1 k
b1 !"
b1 R
b1 _
b1 +
b0 4
b0 =
b0 ,
b1 i
b1 }
b1 Q
b1 e
1#
b10000000 0
b10000000 <
b0 x
b1 s
b10000000 1
b10000000 9
b1 [
b1 5
b1 :
b1 h
b1 6
b1 7
b1 P
b1 &
b1 %
#90000
b111 O
b1111101000000000 +
b1111101000000000 A
b1111101000000000 H
b1111101000000000 )
b1000 C
b1000 G
b1000 N
b0 M
b11111010 B
b11111010 F
b11111010 @
b11111010 I
b11111010 ?
b11111010 K
b1111101000000000 *
b1111101000000000 E
b11111101 0
b11111101 <
b111 D
b111 L
b0 >
b0 J
b11111101 1
b11111101 9
b0 "
b0 ;
b0 !
b0 8
b1111111101 ,
b111 .
b111 /"
0,"
1-"
1."
b11111111010 4
b11111111010 =
b1111111101 -
b111 /
b111 ("
0%"
1&"
1'"
0*"
0+"
0n
0#"
0$"
0V
b1000 r
b1000 Z
0v
b10000000 2
b10000000 l
b10000000 )"
b0 o
0~
1q
0^
b10000000 3
b10000000 T
b10000000 ""
b0 W
0f
1Y
0y
0z
0{
b1000 p
0t
0u
b1000 m
b10 k
b10 !"
0a
0b
0c
b1000 X
0\
0]
b1000 U
b10 S
b10 g
b1000 |
b10001000 j
b1000 w
b11 i
b11 }
b1000 d
b10001000 R
b1000 _
b11 Q
b11 e
b1111 x
b1101 s
b1111 `
b1101 [
b11111101 5
b11111101 :
b11111101 h
b11111101 6
b11111101 7
b11111101 P
b11111101 &
b11111101 %
#100000
1*"
1$"
b10 o
b100 W
b110 "
b110 ;
1n
b101 !
b101 8
1V
b1 .
b1 /"
b10 /
b10 ("
b111 O
b1100 C
b1100 G
b1100 N
b100 M
0-"
0."
1~
0q
0&"
0'"
1f
0Y
1{
b1 k
b1 !"
b1110 *
b1110 E
1c
b1 S
b1 g
b11 D
b11 L
b100 >
b100 J
1z
b10 2
b10 l
b10 )"
b0 r
1u
b1 i
b1 }
b0 A
b0 H
b1110 ?
b1110 K
1b
b100 3
b100 T
b100 ""
b0 Z
b1 Q
b1 e
b1111111111110001 +
1y
b0 p
1t
b10 m
b11100000 B
b11100000 F
b11100000 @
b11100000 I
1a
b0 X
1\
b100 U
b1111111111110001 )
b11000000 ,
b0 |
b10 j
b10 w
b111100000 4
b111100000 =
b100100000 -
b0 d
b100 R
b100 _
b11000000 0
b11000000 <
b0 x
b11 s
b10100000 1
b10100000 9
b0 `
b101 [
1$
b11 5
b11 :
b11 h
b101 6
b101 7
b101 P
b11 &
b100000101 %
#110000
b101 "
b101 ;
b100100000 ,
b10 .
b10 /"
b100100000000000 A
b100100000000000 H
b1111111110110111 +
b100 !
b100 8
0*"
1+"
b1111111110110111 )
b11 /
b11 ("
b1 O
b111 C
b111 G
b111 N
b111 M
1#"
b100 2
b100 l
b100 )"
b100 o
b1001000 *
b1001000 E
b100 m
b110 D
b110 L
b1001000 ?
b1001000 K
b1 >
b1 J
b1000 3
b1000 T
b1000 ""
b1000 W
0u
0v
b100 j
b100 w
b10010000 B
b10010000 F
b10010000 @
b10010000 I
0\
b1000 U
b1100010000 4
b1100010000 =
b111110000 -
b1000 R
b1000 _
b10100000 0
b10100000 <
b101 s
b11110000 1
b11110000 9
b1111 [
b101 5
b101 :
b101 h
b1111 6
b1111 7
b1111 P
b100000101 &
b1111 %
#120000
b11 !
b11 8
b100 /
b100 ("
1%"
b1 O
b111 C
b111 G
b111 N
b111 M
0#"
0$"
0V
b1010000 *
b1010000 E
b1 Z
b101000000000000 A
b101000000000000 H
b110 D
b110 L
b1010000 ?
b1010000 K
b1 >
b1 J
b1 X
b10000 3
b10000 T
b10000 ""
b0 W
0f
1Y
b1010000 +
b10100000 B
b10100000 F
b10100000 @
b10100000 I
b1 d
1\
b100 U
b10 S
b10 g
b1010000 )
b100000000 ,
b1100100000 4
b1100100000 =
b1000100000 -
b10100 R
b100 _
b11 Q
b11 e
b10000000 0
b10000000 <
b100 s
b10100000 1
b10100000 9
b1 `
b100 [
0$
b100 5
b100 :
b100 h
b10100 6
b10100 7
b10100 P
b100000100 &
b100010100 %
#130000
b110 "
b110 ;
1#"
1$"
b100 !
b100 8
1*"
b1 .
b1 /"
b11 /
b11 ("
0+"
b1000 W
0%"
b1 O
b101 C
b101 G
b101 N
b101 M
1V
b10 2
b10 l
b10 )"
b10 o
b10000 *
b10000 E
b1000 3
b1000 T
b1000 ""
b0 Z
b100 D
b100 L
b11 >
b11 J
b10 m
b1111111111101111 +
b1000000000000 A
b1000000000000 H
b10000 ?
b10000 K
b0 X
0^
1f
0Y
1u
b10 j
b10 w
b1111111111101111 )
b10000000 B
b10000000 F
b10000000 @
b10000000 I
b0 d
0\
0]
b1000 U
b1 S
b1 g
b10000000 ,
b1000000000 4
b1000000000 =
b110000000 -
b1000 R
b1000 _
b1 Q
b1 e
b10000000 0
b10000000 <
b10 s
1$
b10000000 1
b10000000 9
b0 `
b1000 [
b10 5
b10 :
b10 h
b1000 6
b1000 7
b1000 P
b10 &
b100001000 %
#140000
b1 C
b1 G
b1 N
b1 M
b101 "
b101 ;
b0 D
b0 L
b111 >
b111 J
0*"
b10 .
b10 /"
b1111111010101111 +
b10 !
b10 8
1+"
b1111111010101111 )
b101 /
b101 ("
1%"
1'"
0#"
0$"
0V
b100 2
b100 l
b100 )"
b100 o
b101010000 *
b101010000 E
b10 Z
b100 m
b101010000 A
b101010000 H
b1 ?
b1 K
b10 X
1]
b100000 3
b100000 T
b100000 ""
b0 W
0f
1Y
0u
b100 j
b100 w
b10101000 B
b10101000 F
b10101000 @
b10101000 I
0c
b10 d
1\
b10 U
b10 S
b10 g
b101100000 ,
b10000101000 4
b10000101000 =
b1011001000 -
b100010 R
b10 _
b11 Q
b11 e
b11100000 0
b11100000 <
b111 s
b11001000 1
b11001000 9
b11 `
b10 [
b111 5
b111 :
b111 h
b110010 6
b110010 7
b110010 P
b100000111 &
b110010 %
#150000
b111 O
b1000 C
b1000 G
b1000 N
b0 M
b10001000 ?
b10001000 K
b111 D
b111 L
b0 >
b0 J
b11 !
b11 8
b100 /
b100 ("
1%"
0'"
b10001000 *
b10001000 E
b10000 3
b10000 T
b10000 ""
b1 Z
b1000100000000000 A
b1000100000000000 H
b1 X
0]
b10001000 +
b10001000 B
b10001000 F
b10001000 @
b10001000 I
1c
b1 d
0\
0^
b1000 U
b10001000 )
b101000000 ,
b1110001000 4
b1110001000 =
b1001001000 -
b11000 R
b1000 _
b11000000 0
b11000000 <
b110 s
b11001000 1
b11001000 9
b1 `
b1001 [
0$
b110 5
b110 :
b110 h
b11001 6
b11001 7
b11001 P
b100000110 &
b100011001 %
