mitchell/LM/mitchell.v
module Barrel8L(
    input [7:0] data_i,
    input [2:0] shift_i,
    output reg [7:0] data_o
    );	 
 
   always @*
      case (shift_i)
         3'd0: data_o = data_i;
         3'd1: data_o = data_i << 1;
         3'd2: data_o = data_i << 2;
         3'd3: data_o = data_i << 3;
         3'd4: data_o = data_i << 4;
         3'd5: data_o = data_i << 5;
         3'd6: data_o = data_i << 6;
         3'd7: data_o = data_i << 7;
      endcase

endmodule


module Barrel8R (
    input [7:0] data_i,
	input [2:0] shift_i,
	output reg [7:0] data_o
    );

	always @*
      case (shift_i)
         3'd0: data_o = data_i;
         3'd1: data_o = data_i >> 1;
         3'd2: data_o = data_i >> 2;
         3'd3: data_o = data_i >> 3;
         3'd4: data_o = data_i >> 4;
         3'd5: data_o = data_i >> 5;
         3'd6: data_o = data_i >> 6;
         3'd7: data_o = data_i >> 7;
      endcase
endmodule


module Barrel16L(
    input [15:0] data_i,
    input [2:0] shift_i,
    output reg [15:0] data_o
    );	 
 
   always @*
      case (shift_i)
         3'd0: data_o = data_i;
         3'd1: data_o = data_i << 1;
         3'd2: data_o = data_i << 2;
         3'd3: data_o = data_i << 3;
         3'd4: data_o = data_i << 4;
         3'd5: data_o = data_i << 5;
         3'd6: data_o = data_i << 6;
         3'd7: data_o = data_i << 7;
      endcase

endmodule


module carry_lookahead_inc(
    input [2:0] i_add1,
    output [2:0] o_result
);
    
    wire [2:0] carry;
    wire [2:0] sum;
    
    // Generate carry signals using lookahead logic
    assign carry[0] = 1'b1; // Incrementing, so initial carry-in is 1
    assign carry[1] = (i_add1[0] & carry[0]);
    assign carry[2] = (i_add1[1] & carry[1]);
    
    // Compute sum bits
    assign sum[0] = i_add1[0] ^ carry[0];
    assign sum[1] = i_add1[1] ^ carry[1];
    assign sum[2] = i_add1[2] ^ carry[2];

    // Output the incremented result
    assign o_result = sum;
    
endmodule


module AntiLog(
    input  [10:0] data_i,   // [10] = lr flag, [9:7] = exponent, [6:0] = fraction
    output [15:0] data_o    // 16-bit approximate product output
);

    // -------------------------------
    // Left Barrel Shift Branch (for lr = 1)
    // -------------------------------
    wire [15:0] l1_in;
    assign l1_in = {8'b0, 1'b1, data_i[6:0]};  // 8 + 1 + 7 = 16 bits

    wire [2:0] k_enc, k_enc_inc;
    assign k_enc = data_i[9:7];  // Extract exponent
    assign k_enc_inc = k_enc + 3'b001;  // Simple increment

    wire [15:0] l1_out;
    Barrel16L L1shift (
        .data_i(l1_in),
        .shift_i(k_enc_inc),
        .data_o(l1_out)
    );

    // -------------------------------
    // Right Barrel Shift Branch (for lr = 0)
    // -------------------------------
    wire [7:0] r_in;
    assign r_in = {1'b1, data_i[6:0]};  // 1 + 7 = 8 bits

    wire [2:0] enc;
    assign enc = ~data_i[9:7] + 3'b001;  // Compute correct right-shift amount

    wire [7:0] r_out;
    Barrel8R Rshift (
        .data_i(r_in),
        .shift_i(enc),
        .data_o(r_out)
    );

    // -------------------------------
    // Output Selection
    // -------------------------------
    wire [7:0] out_msb, out_lsb;
    
    assign out_msb = data_i[10] ? l1_out[15:8] : 8'd0;  // Correct upper bits
    assign out_lsb = data_i[10] ? l1_out[7:0] : r_out;  // Select lower bits
    
    assign data_o = data_i[10] ? l1_out : {8'd0, r_out};  // Full selection

endmodule


module PEncoder (
    input [7:0] A,
    output [2:0] out
);

    wire temp1, temp2, temp3, temp4, temp5;

    assign temp1 = A[1] || A[3];
    assign temp2 = A[2] || A[3];
    assign temp3 = A[4] || A[5];
    assign temp4 = A[6] || A[7];
    assign temp5 = A[5] || A[7];

    assign out[0] = temp1 || temp5;
    assign out[1] = temp2 || temp4;
    assign out[2] = temp3 || temp4;
    
endmodule


module Muxes2in1Array4(
    input [3:0] data_i,
    input select_i,
    output [3:0] data_o
    );

    assign data_o = select_i ? data_i : 4'b0000;

endmodule


module LOD4(
    input [3:0] data_i,
    output [3:0] data_o
    ); 
    wire mux0;
    wire mux1;
    wire mux2;
    
    assign mux2 = (data_i[3] == 1) ? 1'b0 : 1'b1;
    assign mux1 = (data_i[2] == 1) ? 1'b0 : mux2;
    assign mux0 = (data_i[1] == 1) ? 1'b0 : mux1;
    
    assign data_o[3] = data_i[3];
    assign data_o[2] = (mux2 & data_i[2]);
    assign data_o[1] = (mux1 & data_i[1]);
    assign data_o[0] = (mux0 & data_i[0]);
endmodule


module LOD(
    input [7:0] A,
    output zero_o,
    output [7:0] O
    );

    wire [7:0] z;
    wire [1:0] select;
    wire [1:0] zdet;

    LOD4 lod4_1 (
        .data_i(A[7:4]), 
        .data_o(z[7:4])
    );

    LOD4 lod4_0 (
        .data_i(A[3:0]), 
        .data_o(z[3:0])
    );

    LOD4 lod4_middle (
        .data_i({2'b00, zdet}),  // Expand zdet to 4-bit
        .data_o(select) // Expand select to match 4-bit output
    );

    assign zdet[1] = A[7] | A[6] | A[5] | A[4];
    assign zdet[0] = A[3] | A[2] | A[1] | A[0];
    assign zero_o = ~(zdet[1] | zdet[0]);

    Muxes2in1Array4 Inst_MUX214_1 (
        .data_i(z[7:4]), 
        .select_i(select[1]), 
        .data_o(O[7:4])
    );

    Muxes2in1Array4 Inst_MUX214_0 (
        .data_i(z[3:0]), 
        .select_i(select[0]), 
        .data_o(O[3:0])
    );

endmodule


module MITCHEL(
    input [8:0] x,
    input [8:0] y,
    output [16:0] p,

    output [7:0] A,B,
    output [7:0] LODa,LODb,
    output [2:0] kA, kB,   // Expose kA and kB
    output [10:0] op1, op2, L,  // Expose internal values
    output [15:0] tmp_out 
    );

    // wire [7:0] A,B;
    assign A=x[7:0];
    assign B=y[7:0];

    // wire [7:0] LODa,LODb;
    // wire [2:0] kA,kB;
    wire zeroA,zeroB;

    LOD lodA(A,zeroA,LODa);
    LOD lodB(B,zeroB,LODb);

    PEncoder peA(LODa,kA);
    PEncoder peB(LODb,kB);

    wire [2:0] kA_inv;
	wire [7:0] barrelA;
	
	assign kA_inv = ~kA;
	
	Barrel8L BShiftA (
		.data_i(A),
		.shift_i(kA_inv),
		.data_o(barrelA)
 	 ); 

    wire [2:0] kB_inv;
	wire [7:0] barrelB;

	assign kB_inv = ~kB;
	
	Barrel8L BShiftB (
		.data_i(B),
		.shift_i(kB_inv),
		.data_o(barrelB)
 	 );

    // wire [10:0] op1,op2,L;

    assign op1={1'b0,kA,barrelA[6:0]};
    assign op2={1'b0,kB,barrelB[6:0]};

    assign L=op1+op2;

    wire [15:0] tmp_out; 

	AntiLog anti_log(
		.data_i(L),
		.data_o(tmp_out)
	);
	
	wire prod_sign; 
	wire [15:0] tmp_sign;
	
	assign prod_sign = x[8] ^ y[8];
	assign tmp_sign = {17{prod_sign}} ^ tmp_out;
	
	// is zero 
	wire not_zero;
	assign not_zero = (~zeroA | x[8] | x[0]) & (~zeroB | y[8] | y[0]);
	
	assign p = not_zero ? tmp_sign : 16'b0;

endmodule

mitchell/LM/mitchel_tb.v
`timescale 1ns / 1ps

module MITCHEL_tb;

    // Inputs (8-bit unsigned)
    reg [8:0] x, y;
    
    // Outputs
    wire [16:0] p;
    wire [7:0] LODa,LODb,A,B;
    wire [2:0] kA, kB;
    wire [10:0] op1, op2, L;
    wire [15:0] tmp_out;

    // Intermediate signals for signed values
    integer signed_in1, signed_in2, signed_product;

    // Instantiate the ILM module
    MITCHEL uut (
        .x(x), 
        .y(y), 
        .p(p),

        .A(A),
        .B(B),
        .LODa(LODa),
        .LODb(LODb),
        .kA(kA), 
        .kB(kB),
        .op1(op1),
        .op2(op2),
        .L(L),
        .tmp_out(tmp_out)
    );
    
    // Test cases
    initial begin
        // Enable waveform dumping for GTKWave
        $dumpfile("MITCHEL_tb.vcd");  // Name of the VCD file
        $dumpvars(0, uut);      // Dump all variables in this module

        // Monitor output
        $monitor("Time = %0t | x = %d, y = %d | Product = %d | A=%b | B=%b | LODa = %b | LODb=%b | kA = %b | kB = %b | op1 = %b | op2 = %b | L = %b | tmp_out = %b", 
                 $time, x, y, p,A,B,LODa,LODb,kA,kB,op1,op2,L,tmp_out);
        
        // Apply test cases (8-bit unsigned numbers)
        x = 9'd5;  y = 8'd3;  #10;
        x = 9'd15; y = 8'd5;  #10;
        x = 9'd20; y = 8'd4;  #10;
        x = 9'd8;  y = 8'd2;  #10;
        x = 9'd50; y = 8'd7;  #10;
        x = 9'd25; y = 8'd6;  #10;
        x = 9'd129; y = 8'd65;  #10;
        x = 9'd0;  y = 8'd18; #10;
        x = 9'd1;  y = 8'd1;  #10;
        x = 9'd255; y = 8'd255; #10;

        // End simulation
        $finish;
    end

    // Always block to update signed values
    always @(*) begin
        signed_in1 = $signed(x);
        signed_in2 = $signed(y);
        signed_product = $signed(p);
    end
    
endmodule

mitchell/LM/MITCHEL_tb.vcd
$date
	Sun Mar 16 12:13:08 2025
$end
$version
	Icarus Verilog
$end
$timescale
	1ps
$end
$scope module MITCHEL_tb $end
$scope module uut $end
$var wire 3 ! kA_inv [2:0] $end
$var wire 3 " kB_inv [2:0] $end
$var wire 1 # not_zero $end
$var wire 1 $ prod_sign $end
$var wire 9 % x [8:0] $end
$var wire 9 & y [8:0] $end
$var wire 1 ' zeroB $end
$var wire 1 ( zeroA $end
$var wire 16 ) tmp_sign [15:0] $end
$var wire 16 * tmp_out [15:0] $end
$var wire 17 + p [16:0] $end
$var wire 11 , op2 [10:0] $end
$var wire 11 - op1 [10:0] $end
$var wire 3 . kB [2:0] $end
$var wire 3 / kA [2:0] $end
$var wire 8 0 barrelB [7:0] $end
$var wire 8 1 barrelA [7:0] $end
$var wire 8 2 LODb [7:0] $end
$var wire 8 3 LODa [7:0] $end
$var wire 11 4 L [10:0] $end
$var wire 8 5 B [7:0] $end
$var wire 8 6 A [7:0] $end
$scope module BShiftA $end
$var wire 8 7 data_i [7:0] $end
$var wire 3 8 shift_i [2:0] $end
$var reg 8 9 data_o [7:0] $end
$upscope $end
$scope module BShiftB $end
$var wire 8 : data_i [7:0] $end
$var wire 3 ; shift_i [2:0] $end
$var reg 8 < data_o [7:0] $end
$upscope $end
$scope module anti_log $end
$var wire 11 = data_i [10:0] $end
$var wire 8 > r_out [7:0] $end
$var wire 8 ? r_in [7:0] $end
$var wire 8 @ out_msb [7:0] $end
$var wire 8 A out_lsb [7:0] $end
$var wire 16 B l1_out [15:0] $end
$var wire 16 C l1_in [15:0] $end
$var wire 3 D k_enc_inc [2:0] $end
$var wire 3 E k_enc [2:0] $end
$var wire 3 F enc [2:0] $end
$var wire 16 G data_o [15:0] $end
$scope module L1shift $end
$var wire 16 H data_i [15:0] $end
$var wire 3 I shift_i [2:0] $end
$var reg 16 J data_o [15:0] $end
$upscope $end
$scope module Rshift $end
$var wire 8 K data_i [7:0] $end
$var wire 3 L shift_i [2:0] $end
$var reg 8 M data_o [7:0] $end
$upscope $end
$upscope $end
$scope module lodA $end
$var wire 8 N A [7:0] $end
$var wire 1 ( zero_o $end
$var wire 2 O zdet [1:0] $end
$var wire 8 P z [7:0] $end
$var wire 2 Q select [1:0] $end
$var wire 8 R O [7:0] $end
$scope module Inst_MUX214_0 $end
$var wire 4 S data_i [3:0] $end
$var wire 1 T select_i $end
$var wire 4 U data_o [3:0] $end
$upscope $end
$scope module Inst_MUX214_1 $end
$var wire 4 V data_i [3:0] $end
$var wire 1 W select_i $end
$var wire 4 X data_o [3:0] $end
$upscope $end
$scope module lod4_0 $end
$var wire 4 Y data_i [3:0] $end
$var wire 1 Z mux2 $end
$var wire 1 [ mux1 $end
$var wire 1 \ mux0 $end
$var wire 4 ] data_o [3:0] $end
$upscope $end
$scope module lod4_1 $end
$var wire 4 ^ data_i [3:0] $end
$var wire 1 _ mux2 $end
$var wire 1 ` mux1 $end
$var wire 1 a mux0 $end
$var wire 4 b data_o [3:0] $end
$upscope $end
$scope module lod4_middle $end
$var wire 4 c data_i [3:0] $end
$var wire 1 d mux2 $end
$var wire 1 e mux1 $end
$var wire 1 f mux0 $end
$var wire 4 g data_o [3:0] $end
$upscope $end
$upscope $end
$scope module lodB $end
$var wire 8 h A [7:0] $end
$var wire 1 ' zero_o $end
$var wire 2 i zdet [1:0] $end
$var wire 8 j z [7:0] $end
$var wire 2 k select [1:0] $end
$var wire 8 l O [7:0] $end
$scope module Inst_MUX214_0 $end
$var wire 4 m data_i [3:0] $end
$var wire 1 n select_i $end
$var wire 4 o data_o [3:0] $end
$upscope $end
$scope module Inst_MUX214_1 $end
$var wire 4 p data_i [3:0] $end
$var wire 1 q select_i $end
$var wire 4 r data_o [3:0] $end
$upscope $end
$scope module lod4_0 $end
$var wire 4 s data_i [3:0] $end
$var wire 1 t mux2 $end
$var wire 1 u mux1 $end
$var wire 1 v mux0 $end
$var wire 4 w data_o [3:0] $end
$upscope $end
$scope module lod4_1 $end
$var wire 4 x data_i [3:0] $end
$var wire 1 y mux2 $end
$var wire 1 z mux1 $end
$var wire 1 { mux0 $end
$var wire 4 | data_o [3:0] $end
$upscope $end
$scope module lod4_middle $end
$var wire 4 } data_i [3:0] $end
$var wire 1 ~ mux2 $end
$var wire 1 !" mux1 $end
$var wire 1 "" mux0 $end
$var wire 4 #" data_o [3:0] $end
$upscope $end
$upscope $end
$scope module peA $end
$var wire 8 $" A [7:0] $end
$var wire 1 %" temp1 $end
$var wire 1 &" temp2 $end
$var wire 1 '" temp3 $end
$var wire 1 (" temp4 $end
$var wire 1 )" temp5 $end
$var wire 3 *" out [2:0] $end
$upscope $end
$scope module peB $end
$var wire 8 +" A [7:0] $end
$var wire 1 ," temp1 $end
$var wire 1 -" temp2 $end
$var wire 1 ." temp3 $end
$var wire 1 /" temp4 $end
$var wire 1 0" temp5 $end
$var wire 3 1" out [2:0] $end
$upscope $end
$upscope $end
$upscope $end
$enddefinitions $end
#0
$dumpvars
b1 1"
00"
0/"
0."
0-"
1,"
b10 +"
b10 *"
0)"
0("
0'"
1&"
0%"
b100 $"
b1 #"
1""
1!"
1~
b1 }
b0 |
1{
1z
1y
b0 x
b10 w
0v
1u
1t
b11 s
b0 r
0q
b0 p
b10 o
1n
b10 m
b10 l
b1 k
b10 j
b1 i
b11 h
b1 g
1f
1e
1d
b1 c
b0 b
1a
1`
1_
b0 ^
b100 ]
0\
0[
1Z
b101 Y
b0 X
0W
b0 V
b100 U
1T
b100 S
b100 R
b1 Q
b100 P
b1 O
b101 N
b111 M
b101 L
b11100000 K
b111000000000 J
b100 I
b11100000 H
b111 G
b101 F
b11 E
b100 D
b11100000 C
b111000000000 B
b111 A
b0 @
b11100000 ?
b111 >
b111100000 =
b11000000 <
b110 ;
b11 :
b10100000 9
b101 8
b101 7
b101 6
b11 5
b111100000 4
b100 3
b10 2
b10100000 1
b11000000 0
b10 /
b1 .
b100100000 -
b11000000 ,
b111 +
b111 *
b111 )
0(
0'
b11 &
b101 %
0$
1#
b110 "
b101 !
$end
#10000
b101 "
b101 ;
b100100000 ,
b10 .
b10 1"
b100100 +
b100 !
b100 8
0,"
1-"
b100100 )
b11 /
b11 *"
1%"
b100 2
b100 l
b100 +"
b100 o
b100100 *
b100100 G
b100100 A
b100 m
b100100000000000 B
b100100000000000 J
b100100 >
b100100 M
b10 F
b10 L
b1000 3
b1000 R
b1000 $"
b1000 U
0u
0v
b100 j
b100 w
b10010000 C
b10010000 H
b111 D
b111 I
b110 E
b10010000 ?
b10010000 K
0Z
b1000 S
b1100010000 4
b1100010000 =
b111110000 -
b1000 P
b1000 ]
b10100000 0
b10100000 <
b101 s
b11110000 1
b11110000 9
b1111 Y
b101 5
b101 :
b101 h
b1111 6
b1111 7
b1111 N
b101 &
b1111 %
#20000
b0 @
1'"
b101000 +
b11 !
b11 8
b101000 )
b100 /
b100 *"
0T
b1 X
0%"
0&"
1W
b101000 *
b101000 G
b101000 A
b10 Q
b101000000000000 B
b101000000000000 J
b101000 >
b101000 M
b10 F
b10 L
b1 V
b10000 3
b10000 R
b10000 $"
b0 U
0f
b10 g
b10100000 C
b10100000 H
b111 D
b111 I
b110 E
b10100000 ?
b10100000 K
b1 b
1Z
b100 S
b100000000 ,
b1100100000 4
b1100100000 =
b1000100000 -
b10100 P
b100 ]
b11 c
b11 O
b10000000 0
b10000000 <
b100 s
b10100000 1
b10100000 9
b1 ^
b100 Y
b100 5
b100 :
b100 h
b10100 6
b10100 7
b10100 N
b100 &
b10100 %
#30000
1%"
1&"
b110 "
b110 ;
b100 !
b100 8
1,"
b1 .
b1 1"
b1000 +
b11 /
b11 *"
b1000 U
0-"
b1000 )
0'"
1T
0W
b10 2
b10 l
b10 +"
b10 o
b1000 *
b1000 G
b1000 A
b1000 3
b1000 R
b1000 $"
b0 X
b1 Q
b100 F
b100 L
b10 m
b1000000000000 B
b1000000000000 J
b1000 >
b1000 M
b0 V
0\
1f
b1 g
b101 D
b101 I
b100 E
1u
b10 j
b10 w
b10000000 C
b10000000 H
b10000000 ?
b10000000 K
b0 b
0Z
0[
b1000 S
b10000000 ,
b1000000000 4
b1000000000 =
b110000000 -
b1000 P
b1000 ]
b1 c
b1 O
b10000000 0
b10000000 <
b10 s
b10000000 1
b10000000 9
b0 ^
b1000 Y
b10 5
b10 :
b10 h
b1000 6
b1000 7
b1000 N
b10 &
b1000 %
#40000
b1 @
b101 "
b101 ;
b0 F
b0 L
1'"
1)"
0,"
b10 .
b10 1"
b101010000 +
b1 D
b1 I
b0 E
b10 !
b10 8
1-"
b101010000 )
b101 /
b101 *"
0T
b10 X
0%"
0&"
1W
b100 2
b100 l
b100 +"
b100 o
b101010000 *
b101010000 G
b1010000 A
b10 Q
b100 m
b101010000 B
b101010000 J
b10101000 >
b10101000 M
b10 V
1[
b100000 3
b100000 R
b100000 $"
b0 U
0f
b10 g
0u
b100 j
b100 w
b10101000 C
b10101000 H
b10101000 ?
b10101000 K
0a
b10 b
1Z
b10 S
b101100000 ,
b10000101000 4
b10000101000 =
b1011001000 -
b100010 P
b10 ]
b11 c
b11 O
b11100000 0
b11100000 <
b111 s
b11001000 1
b11001000 9
b11 ^
b10 Y
b111 5
b111 :
b111 h
b110010 6
b110010 7
b110010 N
b111 &
b110010 %
#50000
b1 F
b1 L
b0 @
b0 D
b0 I
b111 E
b11 !
b11 8
b1000100 +
b100 /
b100 *"
b1000100 )
1'"
0)"
b1000100 A
b1000100 *
b1000100 G
b10000 3
b10000 R
b10000 $"
b1 X
b10001000 B
b10001000 J
b1000100 >
b1000100 M
b1 V
0[
b10001000 C
b10001000 H
b10001000 ?
b10001000 K
1a
b1 b
0Z
0\
b1000 S
b101000000 ,
b1110001000 4
b1110001000 =
b1001001000 -
b11000 P
b1000 ]
b11000000 0
b11000000 <
b110 s
b11001000 1
b11001000 9
b1 ^
b1001 Y
b110 5
b110 :
b110 h
b11001 6
b11001 7
b11001 N
b110 &
b11001 %
#60000
1/"
b1 "
b1 ;
0n
b100 r
b100000 @
b110 .
b110 1"
1q
b10000011000000 +
b0 !
b0 8
b0 U
0-"
b10 k
b10000011000000 )
b111 /
b111 *"
0T
0""
b10 #"
0'"
1("
1)"
1W
b1000000 2
b1000000 l
b1000000 +"
b0 o
b10000011000000 *
b10000011000000 G
b11000000 A
0a
1\
b10 Q
0{
b100 p
1v
b1 m
b11 }
b11 i
b10000011000000 B
b10000011000000 J
b10000 >
b10000 M
b11 F
b11 L
0`
b10000000 3
b10000000 R
b10000000 $"
b1000 X
1[
0f
b10 g
0z
b100 |
1u
b1000001 j
b1 w
b10000011 C
b10000011 H
b110 D
b110 I
b101 E
b10000011 ?
b10000011 K
0_
b1000 V
1Z
b1 S
b1100000010 ,
b11010000011 4
b11010000011 =
b1110000001 -
b1000 b
b10000001 P
b1 ]
b11 c
b11 O
b10000010 0
b10000010 <
b100 x
b1 s
b10000001 1
b10000001 9
b1000 ^
b1 Y
b1000001 5
b1000001 :
b1000001 h
b10000001 6
b10000001 7
b10000001 N
b1000001 &
b10000001 %
#70000
0#
1."
b11 "
b11 ;
b100 F
b100 L
b100 .
b100 1"
b0 +
b101 D
b101 I
b100 E
b111 !
b111 8
0W
0/"
b1001 )
b0 /
b0 *"
1(
b0 Q
b1001 A
b0 @
0("
0)"
1f
b0 g
b10000 2
b10000 l
b10000 +"
b1 r
b1001 *
b1001 G
1a
1{
b1 p
b10 m
b1001000000000 B
b1001000000000 J
b1001 >
b1001 M
1`
b0 3
b0 R
b0 $"
b0 X
b0 S
1z
b1 |
0v
b10010 j
b10 w
b10010000 C
b10010000 H
b10010000 ?
b10010000 K
1_
b0 V
b0 ]
b1000010000 ,
b11 }
b11 i
b1000010000 4
b1000010000 =
b0 -
b0 P
b0 b
b0 c
b0 O
b10010000 0
b10010000 <
b1 x
b10 s
b0 1
b0 9
b0 ^
b0 Y
b10010 5
b10010 :
b10010 h
b0 6
b0 7
b0 N
b10010 &
b0 %
#80000
b0 F
b0 L
b1 D
b1 I
b0 E
b111 "
b111 ;
b0 .
b0 1"
b1 o
b10000000 )
0."
1n
b1 3
b1 R
b1 $"
b1 U
0q
1T
b10000000 *
b10000000 G
b10000000 A
b1 2
b1 l
b1 +"
b0 r
b1 k
0(
b1 Q
b100000000 B
b100000000 J
b10000000 >
b10000000 M
b0 p
b1 m
1""
b1 #"
b1 S
b1 g
b10000000 C
b10000000 H
b10000000 ?
b10000000 K
b0 |
1v
b1 j
b1 w
b1 P
b1 ]
b10000000 +
b0 4
b0 =
b0 ,
b1 }
b1 i
b1 c
b1 O
1#
b10000000 0
b10000000 <
b0 x
b1 s
b10000000 1
b10000000 9
b1 Y
b1 5
b1 :
b1 h
b1 6
b1 7
b1 N
b1 &
b1 %
#90000
b11111110 +
b11111110 )
b0 @
b11111110 *
b11111110 G
b11111110 A
b11111110 C
b11111110 H
b11111110 ?
b11111110 K
b1111111 >
b1111111 M
b11111111 0
b11111111 <
1/"
10"
b11111110 B
b11111110 J
b1 F
b1 L
b11111111 1
b11111111 9
1("
1)"
b0 "
b0 ;
b0 D
b0 I
b111 E
b0 !
b0 8
b1111111111 ,
b111 .
b111 1"
0n
b1000 r
b11111111110 4
b11111111110 =
b1111111111 -
b111 /
b111 *"
0T
b1000 X
0,"
0-"
1q
0%"
0&"
1W
b10 k
b10 Q
b10000000 2
b10000000 l
b10000000 +"
b0 o
0""
b10 #"
b10000000 3
b10000000 R
b10000000 $"
b0 U
0f
b10 g
0y
0z
0{
b1000 p
0t
0u
0v
b1000 m
0_
0`
0a
b1000 V
0Z
0[
0\
b1000 S
b1000 |
b10001000 j
b1000 w
b11 }
b11 i
b1000 b
b10001000 P
b1000 ]
b11 c
b11 O
b1111 x
b1111 s
b1111 ^
b1111 Y
b11111111 5
b11111111 :
b11111111 h
b11111111 6
b11111111 7
b11111111 N
b11111111 &
b11111111 %
