Wallace_tree/wallace.v
module wallaceTreeMultiplier8Bit (output[15:0] result, input[7:0] a, input[7:0] b);

    reg[7:0] wallaceTree[7:0];
    integer i, j;

    always @(a, b) begin
        for(i = 0;i < 8;i = i+1)
            for(j = 0;j < 8;j = j+1)
                wallaceTree[i][j] = a[i] & b[j];
    end
    // result[0]
    assign result[0] = wallaceTree[0][0];

    // result[1]
    wire result1_c;
    HA result1_HA_1(result1_c, result[1], wallaceTree[0][1], wallaceTree[1][0]);

    // result[2]
    wire result2_c_temp_1, result2_c, result2_temp_1;
    FA result2_FA_1(result2_c_temp_1, result2_temp_1, wallaceTree[0][2], wallaceTree[1][1], result1_c);
    HA result2_HA_1(result2_c, result[2], wallaceTree[2][0], result2_temp_1);

    // result[3]
    wire result3_c_temp_1, result3_c_temp_2, result3_c, result3_temp_1, result3_temp_2;
    FA result3_FA_1(result3_c_temp_1, result3_temp_1, wallaceTree[0][3], wallaceTree[1][2], result2_c);
    FA result3_FA_2(result3_c_temp_2, result3_temp_2, wallaceTree[2][1], result3_temp_1, result2_c_temp_1);
    HA result3_HA_1(result3_c, result[3], wallaceTree[3][0], result3_temp_2);

    // result[4]
    wire result4_c_temp_1, result4_c_temp_2, result4_c_temp_3, result4_c, result4_temp_1, result4_temp_2, result4_temp_3;
    FA result4_FA_1(result4_c_temp_1, result4_temp_1, wallaceTree[0][4], wallaceTree[1][3], result3_c);
    FA result4_FA_2(result4_c_temp_2, result4_temp_2, wallaceTree[2][2], result4_temp_1, result3_c_temp_1);
    FA result4_FA_3(result4_c_temp_3, result4_temp_3, wallaceTree[3][1], result4_temp_2, result3_c_temp_2);
    HA result4_HA_1(result4_c, result[4], wallaceTree[4][0], result4_temp_3);

    // result[5]
    wire result5_c_temp_1, result5_c_temp_2, result5_c_temp_3, result5_c_temp_4, result5_c, result5_temp_1, result5_temp_2, result5_temp_3, result5_temp_4;
    FA result5_FA_1(result5_c_temp_1, result5_temp_1, wallaceTree[0][5], wallaceTree[1][4], result4_c);
    FA result5_FA_2(result5_c_temp_2, result5_temp_2, wallaceTree[2][3], result5_temp_1, result4_c_temp_1);
    FA result5_FA_3(result5_c_temp_3, result5_temp_3, wallaceTree[3][2], result5_temp_2, result4_c_temp_2);
    FA result5_FA_4(result5_c_temp_4, result5_temp_4, wallaceTree[4][1], result5_temp_3, result4_c_temp_3);
    HA result5_HA_1(result5_c, result[5], wallaceTree[5][0], result5_temp_4);

    // result[6]
    wire result6_c_temp_1, result6_c_temp_2, result6_c_temp_3, result6_c_temp_4, result6_c_temp_5, result6_c, result6_temp_1, result6_temp_2, result6_temp_3, result6_temp_4, result6_temp_5;
    FA result6_FA_1(result6_c_temp_1, result6_temp_1, wallaceTree[0][6], wallaceTree[1][5], result5_c);
    FA result6_FA_2(result6_c_temp_2, result6_temp_2, wallaceTree[2][4], result6_temp_1, result5_c_temp_1);
    FA result6_FA_3(result6_c_temp_3, result6_temp_3, wallaceTree[3][3], result6_temp_2, result5_c_temp_2);
    FA result6_FA_4(result6_c_temp_4, result6_temp_4, wallaceTree[4][2], result6_temp_3, result5_c_temp_3);
    FA result6_FA_5(result6_c_temp_5, result6_temp_5, wallaceTree[5][1], result6_temp_4, result5_c_temp_4);
    HA result6_HA_1(result6_c, result[6], wallaceTree[6][0], result6_temp_5);

    // result[7]
    wire result7_c_temp_1, result7_c_temp_2, result7_c_temp_3, result7_c_temp_4, result7_c_temp_5, result7_c_temp_6, result7_c, result7_temp_1, result7_temp_2, result7_temp_3, result7_temp_4, result7_temp_5, result7_temp_6;
    FA result7_FA_1(result7_c_temp_1, result7_temp_1, wallaceTree[0][7], wallaceTree[1][6], result6_c);
    FA result7_FA_2(result7_c_temp_2, result7_temp_2, wallaceTree[2][5], result7_temp_1, result6_c_temp_1);
    FA result7_FA_3(result7_c_temp_3, result7_temp_3, wallaceTree[3][4], result7_temp_2, result6_c_temp_2);
    FA result7_FA_4(result7_c_temp_4, result7_temp_4, wallaceTree[4][3], result7_temp_3, result6_c_temp_3);
    FA result7_FA_5(result7_c_temp_5, result7_temp_5, wallaceTree[5][2], result7_temp_4, result6_c_temp_4);
    FA result7_FA_6(result7_c_temp_6, result7_temp_6, wallaceTree[6][1], result7_temp_5, result6_c_temp_5);
    HA result7_HA_1(result7_c, result[7], wallaceTree[7][0], result7_temp_6);

    // result[8]
    wire result8_c_temp_1, result8_c_temp_2, result8_c_temp_3, result8_c_temp_4, result8_c_temp_5, result8_c_temp_6, result8_c, result8_temp_1, result8_temp_2, result8_temp_3, result8_temp_4, result8_temp_5, result8_temp_6;
    FA result8_FA_1(result8_c_temp_1, result8_temp_1, wallaceTree[1][7], wallaceTree[2][6], result7_c);
    FA result8_FA_2(result8_c_temp_2, result8_temp_2, wallaceTree[3][5], result8_temp_1, result7_c_temp_1);
    FA result8_FA_3(result8_c_temp_3, result8_temp_3, wallaceTree[4][4], result8_temp_2, result7_c_temp_2);
    FA result8_FA_4(result8_c_temp_4, result8_temp_4, wallaceTree[5][3], result8_temp_3, result7_c_temp_3);
    FA result8_FA_5(result8_c_temp_5, result8_temp_5, wallaceTree[6][2], result8_temp_4, result7_c_temp_4);
    FA result8_FA_6(result8_c_temp_6, result8_temp_6, wallaceTree[7][1], result8_temp_5, result7_c_temp_5);
    HA result8_HA_1(result8_c, result[8], result8_temp_6, result7_c_temp_6);

    // result[9]
    wire result9_c_temp_1, result9_c_temp_2, result9_c_temp_3, result9_c_temp_4, result9_c_temp_5, result9_c, result9_temp_1, result9_temp_2, result9_temp_3, result9_temp_4, result9_temp_5;
    FA result9_FA_1(result9_c_temp_1, result9_temp_1, wallaceTree[2][7], wallaceTree[3][6], result8_c);
    FA result9_FA_2(result9_c_temp_2, result9_temp_2, wallaceTree[4][5], result9_temp_1, result8_c_temp_1);
    FA result9_FA_3(result9_c_temp_3, result9_temp_3, wallaceTree[5][4], result9_temp_2, result8_c_temp_2);
    FA result9_FA_4(result9_c_temp_4, result9_temp_4, wallaceTree[6][3], result9_temp_3, result8_c_temp_3);
    FA result9_FA_5(result9_c_temp_5, result9_temp_5, wallaceTree[7][2], result9_temp_4, result8_c_temp_4);
    FA result9_FA_6(result9_c, result[9], result9_temp_5, result8_c_temp_5, result8_c_temp_6);

    // result[10]
    wire result10_c_temp_1, result10_c_temp_2, result10_c_temp_3, result10_c_temp_4, result10_c, result10_temp_1, result10_temp_2, result10_temp_3, result10_temp_4;
    FA result10_FA_1(result10_c_temp_1, result10_temp_1, wallaceTree[3][7], wallaceTree[4][6], result9_c);
    FA result10_FA_2(result10_c_temp_2, result10_temp_2, wallaceTree[5][5], result10_temp_1, result9_c_temp_1);
    FA result10_FA_3(result10_c_temp_3, result10_temp_3, wallaceTree[6][4], result10_temp_2, result9_c_temp_2);
    FA result10_FA_4(result10_c_temp_4, result10_temp_4, wallaceTree[7][3], result10_temp_3, result9_c_temp_3);
    FA result10_FA_5(result10_c, result[10], result10_temp_4, result9_c_temp_4, result9_c_temp_5);

    // result[11]
    wire result11_c_temp_1, result11_c_temp_2, result11_c_temp_3, result11_c, result11_temp_1, result11_temp_2, result11_temp_3;
    FA result11_FA_1(result11_c_temp_1, result11_temp_1, wallaceTree[4][7], wallaceTree[5][6], result10_c);
    FA result11_FA_2(result11_c_temp_2, result11_temp_2, wallaceTree[6][5], result11_temp_1, result10_c_temp_1);
    FA result11_FA_3(result11_c_temp_3, result11_temp_3, wallaceTree[7][4], result11_temp_2, result10_c_temp_2);
    FA result11_FA_4(result11_c, result[11], result11_temp_3, result10_c_temp_3, result10_c_temp_4);

    // result[12]
    wire result12_c_temp_1, result12_c_temp_2, result12_c, result12_temp_1, result12_temp_2;
    FA result12_FA_1(result12_c_temp_1, result12_temp_1, wallaceTree[5][7], wallaceTree[6][6], result11_c);
    FA result12_FA_2(result12_c_temp_2, result12_temp_2, wallaceTree[7][5], result12_temp_1, result11_c_temp_1);
    FA result12_FA_3(result12_c, result[12], result12_temp_2, result11_c_temp_2, result11_c_temp_3);

    // result[13]
    wire result13_c_temp_1, result13_c, result13_temp_1;
    FA result13_FA_1(result13_c_temp_1, result13_temp_1, wallaceTree[6][7], wallaceTree[7][6], result12_c);
    FA result13_FA_2(result13_c, result[13], result13_temp_1, result12_c_temp_2, result12_c_temp_1);

    // result[14]
    wire result14_c;
    FA result14_FA_1(result14_c, result[14], wallaceTree[7][7], result13_c, result13_c_temp_1);

    // result[15]
    assign result[15] = result14_c;
endmodule

// Missing module definitions for HA and FA

// Half Adder
module HA(output c, output s, input a, input b);
    assign s = a ^ b;
    assign c = a & b;
endmodule

// Full Adder
module FA(output c, output s, input a, input b, input cin);
    assign s = a ^ b ^ cin;
    assign c = (a & b) | (b & cin) | (a & cin);
endmodule

Wallace_tree/wallace_tb.v
`timescale 1ns/1ps

module wallaceTreeMultiplier8Bit_tb;
    // Inputs
    reg [7:0] a;
    reg [7:0] b;
    
    // Outputs
    wire [15:0] result;
    
    // Expected output for verification
    reg [15:0] expected_result;
    
    wallaceTreeMultiplier8Bit uut (
        .result(result),
        .a(a),
        .b(b)
    );
    
    integer errors = 0;
    integer tests = 0;
    
    initial begin
    	$dumpfile("wallace_tree_multiplier_tb.vcd");
        $dumpvars(0, wallaceTreeMultiplier8Bit_tb);
        // Initialize inputs
        a = 0;
        b = 0;
        
        #100;
        
        // Test cases
        // Test Case 1: 0 * 0 = 0
        a = 8'd0; b = 8'd0;
        expected_result = a * b;
        #10;
        verify_result;
        
        // Test Case 2: 1 * 1 = 1
        a = 8'd1; b = 8'd1;
        expected_result = a * b;
        #10;
        verify_result;
        
        // Test Case 3: 7*5=35
        a = 8'd5; b = 8'd7;
        expected_result = a * b;
        #10;
        verify_result;
        
        // Test Case 4: 15*16=240
        a = 8'd15; b = 8'd16;
        expected_result = a * b;
        #10;
        verify_result;
        
        // Test Case 5: 255 * 1=255
        a = 8'd255; b = 8'd1;
        expected_result = a * b;
        #10;
        verify_result;
        
        // Test Case 6: 255 * 2=510
        a = 8'd255; b = 8'd2;
        expected_result = a * b;
        #10;
        verify_result;
        
        // Test Case 7: 255*255=65025
        a = 8'd255; b = 8'd255;
        expected_result = a * b;
        #10;
        verify_result;
        
        // Test Case 8: 123*45=5535
        a = 8'd123; b = 8'd45;
        expected_result = a * b;
        #10;
        verify_result;
        
        // Test Case 9: 200*100=20000
        a = 8'd200; b = 8'd100;
        expected_result = a * b;
        #10;
        verify_result;
        
        // Test Case 10: 85*85=7225
        a = 8'd85; b = 8'd85;
        expected_result = a * b;
        #10;
        verify_result;
        
        if (errors != 0) begin
            $display("TESTBENCH FAILED! %0d out of %0d tests failed.", errors, tests);
        end
        
        $finish;
    end
    
    // Task to verify the result against expected value
    task verify_result;
    begin
        tests = tests + 1;
        if (result !== expected_result) begin
            $display("ERROR at time %0t: a=%0d, b=%0d, result=%0d, expected=%0d", 
                     $time, a, b, result, expected_result);
            errors = errors + 1;
        end else begin
            $display("PASS at time %0t: a=%0d, b=%0d, result=%0d", 
                     $time, a, b, result);
        end
    end
    endtask
    
endmodule

Wallace_tree/wallace_tree_multiplier_tb.vcd
$date
	Mon Mar 17 23:52:22 2025
$end
$version
	Icarus Verilog
$end
$timescale
	1ps
$end
$scope module wallaceTreeMultiplier8Bit_tb $end
$var wire 16 ! result [15:0] $end
$var reg 8 " a [7:0] $end
$var reg 8 # b [7:0] $end
$var reg 16 $ expected_result [15:0] $end
$var integer 32 % errors [31:0] $end
$var integer 32 & tests [31:0] $end
$scope module uut $end
$var wire 8 ' a [7:0] $end
$var wire 8 ( b [7:0] $end
$var wire 1 ) result9_temp_5 $end
$var wire 1 * result9_temp_4 $end
$var wire 1 + result9_temp_3 $end
$var wire 1 , result9_temp_2 $end
$var wire 1 - result9_temp_1 $end
$var wire 1 . result9_c_temp_5 $end
$var wire 1 / result9_c_temp_4 $end
$var wire 1 0 result9_c_temp_3 $end
$var wire 1 1 result9_c_temp_2 $end
$var wire 1 2 result9_c_temp_1 $end
$var wire 1 3 result9_c $end
$var wire 1 4 result8_temp_6 $end
$var wire 1 5 result8_temp_5 $end
$var wire 1 6 result8_temp_4 $end
$var wire 1 7 result8_temp_3 $end
$var wire 1 8 result8_temp_2 $end
$var wire 1 9 result8_temp_1 $end
$var wire 1 : result8_c_temp_6 $end
$var wire 1 ; result8_c_temp_5 $end
$var wire 1 < result8_c_temp_4 $end
$var wire 1 = result8_c_temp_3 $end
$var wire 1 > result8_c_temp_2 $end
$var wire 1 ? result8_c_temp_1 $end
$var wire 1 @ result8_c $end
$var wire 1 A result7_temp_6 $end
$var wire 1 B result7_temp_5 $end
$var wire 1 C result7_temp_4 $end
$var wire 1 D result7_temp_3 $end
$var wire 1 E result7_temp_2 $end
$var wire 1 F result7_temp_1 $end
$var wire 1 G result7_c_temp_6 $end
$var wire 1 H result7_c_temp_5 $end
$var wire 1 I result7_c_temp_4 $end
$var wire 1 J result7_c_temp_3 $end
$var wire 1 K result7_c_temp_2 $end
$var wire 1 L result7_c_temp_1 $end
$var wire 1 M result7_c $end
$var wire 1 N result6_temp_5 $end
$var wire 1 O result6_temp_4 $end
$var wire 1 P result6_temp_3 $end
$var wire 1 Q result6_temp_2 $end
$var wire 1 R result6_temp_1 $end
$var wire 1 S result6_c_temp_5 $end
$var wire 1 T result6_c_temp_4 $end
$var wire 1 U result6_c_temp_3 $end
$var wire 1 V result6_c_temp_2 $end
$var wire 1 W result6_c_temp_1 $end
$var wire 1 X result6_c $end
$var wire 1 Y result5_temp_4 $end
$var wire 1 Z result5_temp_3 $end
$var wire 1 [ result5_temp_2 $end
$var wire 1 \ result5_temp_1 $end
$var wire 1 ] result5_c_temp_4 $end
$var wire 1 ^ result5_c_temp_3 $end
$var wire 1 _ result5_c_temp_2 $end
$var wire 1 ` result5_c_temp_1 $end
$var wire 1 a result5_c $end
$var wire 1 b result4_temp_3 $end
$var wire 1 c result4_temp_2 $end
$var wire 1 d result4_temp_1 $end
$var wire 1 e result4_c_temp_3 $end
$var wire 1 f result4_c_temp_2 $end
$var wire 1 g result4_c_temp_1 $end
$var wire 1 h result4_c $end
$var wire 1 i result3_temp_2 $end
$var wire 1 j result3_temp_1 $end
$var wire 1 k result3_c_temp_2 $end
$var wire 1 l result3_c_temp_1 $end
$var wire 1 m result3_c $end
$var wire 1 n result2_temp_1 $end
$var wire 1 o result2_c_temp_1 $end
$var wire 1 p result2_c $end
$var wire 1 q result1_c $end
$var wire 1 r result14_c $end
$var wire 1 s result13_temp_1 $end
$var wire 1 t result13_c_temp_1 $end
$var wire 1 u result13_c $end
$var wire 1 v result12_temp_2 $end
$var wire 1 w result12_temp_1 $end
$var wire 1 x result12_c_temp_2 $end
$var wire 1 y result12_c_temp_1 $end
$var wire 1 z result12_c $end
$var wire 1 { result11_temp_3 $end
$var wire 1 | result11_temp_2 $end
$var wire 1 } result11_temp_1 $end
$var wire 1 ~ result11_c_temp_3 $end
$var wire 1 !" result11_c_temp_2 $end
$var wire 1 "" result11_c_temp_1 $end
$var wire 1 #" result11_c $end
$var wire 1 $" result10_temp_4 $end
$var wire 1 %" result10_temp_3 $end
$var wire 1 &" result10_temp_2 $end
$var wire 1 '" result10_temp_1 $end
$var wire 1 (" result10_c_temp_4 $end
$var wire 1 )" result10_c_temp_3 $end
$var wire 1 *" result10_c_temp_2 $end
$var wire 1 +" result10_c_temp_1 $end
$var wire 1 ," result10_c $end
$var wire 16 -" result [15:0] $end
$var integer 32 ." i [31:0] $end
$var integer 32 /" j [31:0] $end
$scope module result10_FA_1 $end
$var wire 1 0" a $end
$var wire 1 1" b $end
$var wire 1 +" c $end
$var wire 1 '" s $end
$var wire 1 3 cin $end
$upscope $end
$scope module result10_FA_2 $end
$var wire 1 2" a $end
$var wire 1 '" b $end
$var wire 1 *" c $end
$var wire 1 &" s $end
$var wire 1 2 cin $end
$upscope $end
$scope module result10_FA_3 $end
$var wire 1 3" a $end
$var wire 1 &" b $end
$var wire 1 )" c $end
$var wire 1 %" s $end
$var wire 1 1 cin $end
$upscope $end
$scope module result10_FA_4 $end
$var wire 1 4" a $end
$var wire 1 %" b $end
$var wire 1 (" c $end
$var wire 1 $" s $end
$var wire 1 0 cin $end
$upscope $end
$scope module result10_FA_5 $end
$var wire 1 $" a $end
$var wire 1 ," c $end
$var wire 1 5" s $end
$var wire 1 . cin $end
$var wire 1 / b $end
$upscope $end
$scope module result11_FA_1 $end
$var wire 1 6" a $end
$var wire 1 7" b $end
$var wire 1 "" c $end
$var wire 1 ," cin $end
$var wire 1 } s $end
$upscope $end
$scope module result11_FA_2 $end
$var wire 1 8" a $end
$var wire 1 } b $end
$var wire 1 !" c $end
$var wire 1 +" cin $end
$var wire 1 | s $end
$upscope $end
$scope module result11_FA_3 $end
$var wire 1 9" a $end
$var wire 1 | b $end
$var wire 1 ~ c $end
$var wire 1 *" cin $end
$var wire 1 { s $end
$upscope $end
$scope module result11_FA_4 $end
$var wire 1 { a $end
$var wire 1 )" b $end
$var wire 1 #" c $end
$var wire 1 (" cin $end
$var wire 1 :" s $end
$upscope $end
$scope module result12_FA_1 $end
$var wire 1 ;" a $end
$var wire 1 <" b $end
$var wire 1 y c $end
$var wire 1 #" cin $end
$var wire 1 w s $end
$upscope $end
$scope module result12_FA_2 $end
$var wire 1 =" a $end
$var wire 1 w b $end
$var wire 1 x c $end
$var wire 1 "" cin $end
$var wire 1 v s $end
$upscope $end
$scope module result12_FA_3 $end
$var wire 1 v a $end
$var wire 1 !" b $end
$var wire 1 z c $end
$var wire 1 ~ cin $end
$var wire 1 >" s $end
$upscope $end
$scope module result13_FA_1 $end
$var wire 1 ?" a $end
$var wire 1 @" b $end
$var wire 1 t c $end
$var wire 1 z cin $end
$var wire 1 s s $end
$upscope $end
$scope module result13_FA_2 $end
$var wire 1 s a $end
$var wire 1 x b $end
$var wire 1 u c $end
$var wire 1 y cin $end
$var wire 1 A" s $end
$upscope $end
$scope module result14_FA_1 $end
$var wire 1 B" a $end
$var wire 1 u b $end
$var wire 1 r c $end
$var wire 1 t cin $end
$var wire 1 C" s $end
$upscope $end
$scope module result1_HA_1 $end
$var wire 1 D" a $end
$var wire 1 E" b $end
$var wire 1 q c $end
$var wire 1 F" s $end
$upscope $end
$scope module result2_FA_1 $end
$var wire 1 G" a $end
$var wire 1 H" b $end
$var wire 1 o c $end
$var wire 1 q cin $end
$var wire 1 n s $end
$upscope $end
$scope module result2_HA_1 $end
$var wire 1 I" a $end
$var wire 1 n b $end
$var wire 1 p c $end
$var wire 1 J" s $end
$upscope $end
$scope module result3_FA_1 $end
$var wire 1 K" a $end
$var wire 1 L" b $end
$var wire 1 l c $end
$var wire 1 p cin $end
$var wire 1 j s $end
$upscope $end
$scope module result3_FA_2 $end
$var wire 1 M" a $end
$var wire 1 j b $end
$var wire 1 k c $end
$var wire 1 o cin $end
$var wire 1 i s $end
$upscope $end
$scope module result3_HA_1 $end
$var wire 1 N" a $end
$var wire 1 i b $end
$var wire 1 m c $end
$var wire 1 O" s $end
$upscope $end
$scope module result4_FA_1 $end
$var wire 1 P" a $end
$var wire 1 Q" b $end
$var wire 1 g c $end
$var wire 1 m cin $end
$var wire 1 d s $end
$upscope $end
$scope module result4_FA_2 $end
$var wire 1 R" a $end
$var wire 1 d b $end
$var wire 1 f c $end
$var wire 1 l cin $end
$var wire 1 c s $end
$upscope $end
$scope module result4_FA_3 $end
$var wire 1 S" a $end
$var wire 1 c b $end
$var wire 1 e c $end
$var wire 1 k cin $end
$var wire 1 b s $end
$upscope $end
$scope module result4_HA_1 $end
$var wire 1 T" a $end
$var wire 1 b b $end
$var wire 1 h c $end
$var wire 1 U" s $end
$upscope $end
$scope module result5_FA_1 $end
$var wire 1 V" a $end
$var wire 1 W" b $end
$var wire 1 ` c $end
$var wire 1 h cin $end
$var wire 1 \ s $end
$upscope $end
$scope module result5_FA_2 $end
$var wire 1 X" a $end
$var wire 1 \ b $end
$var wire 1 _ c $end
$var wire 1 g cin $end
$var wire 1 [ s $end
$upscope $end
$scope module result5_FA_3 $end
$var wire 1 Y" a $end
$var wire 1 [ b $end
$var wire 1 ^ c $end
$var wire 1 f cin $end
$var wire 1 Z s $end
$upscope $end
$scope module result5_FA_4 $end
$var wire 1 Z" a $end
$var wire 1 Z b $end
$var wire 1 ] c $end
$var wire 1 e cin $end
$var wire 1 Y s $end
$upscope $end
$scope module result5_HA_1 $end
$var wire 1 [" a $end
$var wire 1 Y b $end
$var wire 1 a c $end
$var wire 1 \" s $end
$upscope $end
$scope module result6_FA_1 $end
$var wire 1 ]" a $end
$var wire 1 ^" b $end
$var wire 1 W c $end
$var wire 1 a cin $end
$var wire 1 R s $end
$upscope $end
$scope module result6_FA_2 $end
$var wire 1 _" a $end
$var wire 1 R b $end
$var wire 1 V c $end
$var wire 1 ` cin $end
$var wire 1 Q s $end
$upscope $end
$scope module result6_FA_3 $end
$var wire 1 `" a $end
$var wire 1 Q b $end
$var wire 1 U c $end
$var wire 1 _ cin $end
$var wire 1 P s $end
$upscope $end
$scope module result6_FA_4 $end
$var wire 1 a" a $end
$var wire 1 P b $end
$var wire 1 T c $end
$var wire 1 ^ cin $end
$var wire 1 O s $end
$upscope $end
$scope module result6_FA_5 $end
$var wire 1 b" a $end
$var wire 1 O b $end
$var wire 1 S c $end
$var wire 1 ] cin $end
$var wire 1 N s $end
$upscope $end
$scope module result6_HA_1 $end
$var wire 1 c" a $end
$var wire 1 N b $end
$var wire 1 X c $end
$var wire 1 d" s $end
$upscope $end
$scope module result7_FA_1 $end
$var wire 1 e" a $end
$var wire 1 f" b $end
$var wire 1 L c $end
$var wire 1 X cin $end
$var wire 1 F s $end
$upscope $end
$scope module result7_FA_2 $end
$var wire 1 g" a $end
$var wire 1 F b $end
$var wire 1 K c $end
$var wire 1 W cin $end
$var wire 1 E s $end
$upscope $end
$scope module result7_FA_3 $end
$var wire 1 h" a $end
$var wire 1 E b $end
$var wire 1 J c $end
$var wire 1 V cin $end
$var wire 1 D s $end
$upscope $end
$scope module result7_FA_4 $end
$var wire 1 i" a $end
$var wire 1 D b $end
$var wire 1 I c $end
$var wire 1 U cin $end
$var wire 1 C s $end
$upscope $end
$scope module result7_FA_5 $end
$var wire 1 j" a $end
$var wire 1 C b $end
$var wire 1 H c $end
$var wire 1 T cin $end
$var wire 1 B s $end
$upscope $end
$scope module result7_FA_6 $end
$var wire 1 k" a $end
$var wire 1 B b $end
$var wire 1 G c $end
$var wire 1 S cin $end
$var wire 1 A s $end
$upscope $end
$scope module result7_HA_1 $end
$var wire 1 l" a $end
$var wire 1 A b $end
$var wire 1 M c $end
$var wire 1 m" s $end
$upscope $end
$scope module result8_FA_1 $end
$var wire 1 n" a $end
$var wire 1 o" b $end
$var wire 1 ? c $end
$var wire 1 M cin $end
$var wire 1 9 s $end
$upscope $end
$scope module result8_FA_2 $end
$var wire 1 p" a $end
$var wire 1 9 b $end
$var wire 1 > c $end
$var wire 1 L cin $end
$var wire 1 8 s $end
$upscope $end
$scope module result8_FA_3 $end
$var wire 1 q" a $end
$var wire 1 8 b $end
$var wire 1 = c $end
$var wire 1 K cin $end
$var wire 1 7 s $end
$upscope $end
$scope module result8_FA_4 $end
$var wire 1 r" a $end
$var wire 1 7 b $end
$var wire 1 < c $end
$var wire 1 J cin $end
$var wire 1 6 s $end
$upscope $end
$scope module result8_FA_5 $end
$var wire 1 s" a $end
$var wire 1 6 b $end
$var wire 1 ; c $end
$var wire 1 I cin $end
$var wire 1 5 s $end
$upscope $end
$scope module result8_FA_6 $end
$var wire 1 t" a $end
$var wire 1 5 b $end
$var wire 1 : c $end
$var wire 1 H cin $end
$var wire 1 4 s $end
$upscope $end
$scope module result8_HA_1 $end
$var wire 1 4 a $end
$var wire 1 G b $end
$var wire 1 @ c $end
$var wire 1 u" s $end
$upscope $end
$scope module result9_FA_1 $end
$var wire 1 v" a $end
$var wire 1 w" b $end
$var wire 1 2 c $end
$var wire 1 @ cin $end
$var wire 1 - s $end
$upscope $end
$scope module result9_FA_2 $end
$var wire 1 x" a $end
$var wire 1 - b $end
$var wire 1 1 c $end
$var wire 1 ? cin $end
$var wire 1 , s $end
$upscope $end
$scope module result9_FA_3 $end
$var wire 1 y" a $end
$var wire 1 , b $end
$var wire 1 0 c $end
$var wire 1 > cin $end
$var wire 1 + s $end
$upscope $end
$scope module result9_FA_4 $end
$var wire 1 z" a $end
$var wire 1 + b $end
$var wire 1 / c $end
$var wire 1 = cin $end
$var wire 1 * s $end
$upscope $end
$scope module result9_FA_5 $end
$var wire 1 {" a $end
$var wire 1 * b $end
$var wire 1 . c $end
$var wire 1 < cin $end
$var wire 1 ) s $end
$upscope $end
$scope module result9_FA_6 $end
$var wire 1 ) a $end
$var wire 1 ; b $end
$var wire 1 3 c $end
$var wire 1 : cin $end
$var wire 1 |" s $end
$upscope $end
$upscope $end
$scope task verify_result $end
$upscope $end
$upscope $end
$enddefinitions $end
#0
$dumpvars
0|"
0{"
0z"
0y"
0x"
0w"
0v"
0u"
0t"
0s"
0r"
0q"
0p"
0o"
0n"
0m"
0l"
0k"
0j"
0i"
0h"
0g"
0f"
0e"
0d"
0c"
0b"
0a"
0`"
0_"
0^"
0]"
0\"
0["
0Z"
0Y"
0X"
0W"
0V"
0U"
0T"
0S"
0R"
0Q"
0P"
0O"
0N"
0M"
0L"
0K"
0J"
0I"
0H"
0G"
0F"
0E"
0D"
0C"
0B"
0A"
0@"
0?"
0>"
0="
0<"
0;"
0:"
09"
08"
07"
06"
05"
04"
03"
02"
01"
00"
b1000 /"
b1000 ."
b0 -"
0,"
0+"
0*"
0)"
0("
0'"
0&"
0%"
0$"
0#"
0""
0!"
0~
0}
0|
0{
0z
0y
0x
0w
0v
0u
0t
0s
0r
0q
0p
0o
0n
0m
0l
0k
0j
0i
0h
0g
0f
0e
0d
0c
0b
0a
0`
0_
0^
0]
0\
0[
0Z
0Y
0X
0W
0V
0U
0T
0S
0R
0Q
0P
0O
0N
0M
0L
0K
0J
0I
0H
0G
0F
0E
0D
0C
0B
0A
0@
0?
0>
0=
0<
0;
0:
09
08
07
06
05
04
03
02
01
00
0/
0.
0-
0,
0+
0*
0)
b0 (
b0 '
b0 &
b0 %
bx $
b0 #
b0 "
b0 !
$end
#100000
b0 $
#110000
b1 !
b1 -"
b1000 /"
b1000 ."
b1 $
b1 #
b1 (
b1 "
b1 '
b1 &
#120000
1\"
1Y
1e
1k
0U"
0b
1j
0O"
1p
1c
0i
1n
0J"
b100011 !
b100011 -"
1F"
1R"
1M"
1I"
1G"
1D"
b1000 /"
b1000 ."
b100011 $
b111 #
b111 (
b101 "
b101 '
b10 &
#130000
1m"
1d"
1A
1N
1\"
1U"
1B
1O
1Y
1Z
1b
0e
1C
1P
1[
0O"
0k
1D
1Q
1c
0i
0j
1\
1d
0n
0J"
0p
0F"
1h"
1_"
0R"
0M"
0I"
1W"
1P"
0G"
0D"
b11110000 !
b11110000 -"
b1000 /"
b1000 ."
b11110000 $
b10000 #
b10000 (
b1111 "
b1111 '
b11 &
#140000
0Y
0u"
04
0Z
05
0[
06
0A
0N
0\
07
0B
0O
0b
08
0E
0C
0P
0c
09
0F
0R
0D
0Q
0d
1m"
0M
1d"
0X
1\"
0a
1U"
0h
1O"
1J"
1F"
1l"
1c"
1["
1T"
0h"
1N"
0_"
1I"
0W"
1E"
0P"
b11111111 !
b11111111 -"
b1000 /"
b1000 ."
b11111111 $
b1 #
b1 (
b11111111 "
b11111111 '
b100 &
#150000
1u"
14
1A
1N
1Y
1b
1i
1n
1m"
1d"
1\"
1U"
1O"
1J"
1t"
0l"
1k"
0c"
1b"
0["
1Z"
0T"
1S"
0N"
1M"
0I"
1H"
0E"
1D"
b111111110 !
b111111110 -"
b1000 /"
b1000 ."
b111111110 $
b10 #
b10 (
b101 &
#160000
1-
0u"
1@
1w
1}
1'"
1s
1#"
1,"
13
1u
1z
1r
1~
1("
1.
1:
1)"
1/
1;
1G
1x
10
1<
1H
1S
1!"
1=
1I
1T
1]
1*"
1J
1U
1^
1e
11
1>
1K
1V
1_
1f
1k
1>"
1:"
15"
1|"
14
1A"
1A
1N
1Y
1b
1t
1y
1""
1+"
12
1?
1L
1W
1`
1g
1l
1o
1C"
1v
1{
1$"
1)
19
1|
1%"
1*
15
1F
1&"
1+
16
1B
1R
1,
17
1C
1O
1\
18
1D
1P
1Z
1d
1E
1Q
1[
1c
1j
0m"
1M
0d"
1X
0\"
1a
0U"
1h
0O"
1m
0J"
1p
0F"
1q
1B"
1@"
1="
19"
14"
1{"
1l"
1?"
1<"
18"
13"
1z"
1s"
1c"
1;"
17"
12"
1y"
1r"
1j"
1["
16"
11"
1x"
1q"
1i"
1a"
1T"
10"
1w"
1p"
1h"
1`"
1Y"
1N"
1v"
1o"
1g"
1_"
1X"
1R"
1I"
1n"
1f"
1^"
1W"
1Q"
1L"
1E"
1e"
1]"
1V"
1P"
1K"
1G"
b1111111000000001 !
b1111111000000001 -"
b1000 /"
b1000 ."
b1111111000000001 $
b11111111 #
b11111111 (
b110 &
