ILM/PriorityEncoder/PEncoder.v

module PEncoder (
    input [7:0] A,
    output [2:0] out
);

    wire temp1, temp2, temp3, temp4, temp5;

    assign temp1 = A[1] || A[3];
    assign temp2 = A[2] || A[3];
    assign temp3 = A[4] || A[5];
    assign temp4 = A[6] || A[7];
    assign temp5 = A[5] || A[7];

    assign out[0] = temp1 || temp5;
    assign out[1] = temp2 || temp4;
    assign out[2] = temp3 || temp4;
    
endmodule

ILM/PriorityEncoder/PEncoder_tb.v
`timescale 1ns / 1ps

module PEncoder_tb;
    
    reg [7:0] A;
    wire [2:0] O;
    
    // Instantiate the PEncoder module
    PEncoder uut (
        .A(A),
        .out(O)
    );
    
    initial begin
        // Dump waves for GTKWave
        $dumpfile("pencoder_tb.vcd");
        $dumpvars(0, PEncoder_tb);
        
        // Monitor signals
        $monitor("Time=%0t A=%d O=%d", $time, A, O);
        
        // Apply test vectors
        A = 8'd0; #10; // Test case 1: All zeros
        A = 8'd1; #10; // Test case 2: Single 1 at LSB
        A = 8'd2; #10; // Test case 3: Single 1 at bit 1
        A = 8'd35; #10; // Test case 4: First three bits high
        A = 8'd64; #10; // Test case 5: Random middle bits
        A = 8'd128; #10; // Test case 6: Alternating bits
        A = 8'd250; #10; // Test case 7: All ones
        A = 8'd73; #10; // Test case 8: Single 1 at MSB
        
        // End simulation
        $finish;
    end
    
endmodule

ILM/PriorityEncoder/pencoder_tb.vcd
$date
	Sat Mar  8 13:31:53 2025
$end
$version
	Icarus Verilog
$end
$timescale
	1ps
$end
$scope module PEncoder_tb $end
$var wire 3 ! O [2:0] $end
$var reg 8 " A [7:0] $end
$scope module uut $end
$var wire 8 # A [7:0] $end
$var wire 1 $ temp1 $end
$var wire 1 % temp2 $end
$var wire 1 & temp3 $end
$var wire 1 ' temp4 $end
$var wire 1 ( temp5 $end
$var wire 3 ) out [2:0] $end
$upscope $end
$upscope $end
$enddefinitions $end
$comment Show the parameter values. $end
$dumpall
$end
#0
$dumpvars
b0 )
0(
0'
0&
0%
0$
b0 #
b0 "
b0 !
$end
#10000
b1 "
b1 #
#20000
b1 !
b1 )
1$
b10 "
b10 #
#30000
b101 !
b101 )
1&
1(
b100011 "
b100011 #
#40000
b110 !
b110 )
0$
0&
1'
0(
b1000000 "
b1000000 #
#50000
b111 !
b111 )
1(
b10000000 "
b10000000 #
#60000
1$
1%
1&
b11111010 "
b11111010 #
#70000
0&
0(
b1001001 "
b1001001 #
