mitchell/NOD/LOD.v
module Muxes2in1Array4(
    input [3:0] data_i,
    input select_i,
    output [3:0] data_o
    );

    assign data_o = select_i ? data_i : 4'b0000;

endmodule


module LOD4(
    input [3:0] data_i,
    output [3:0] data_o
    ); 
    wire mux0;
    wire mux1;
    wire mux2;
    
    assign mux2 = (data_i[3] == 1) ? 1'b0 : 1'b1;
    assign mux1 = (data_i[2] == 1) ? 1'b0 : mux2;
    assign mux0 = (data_i[1] == 1) ? 1'b0 : mux1;
    
    assign data_o[3] = data_i[3];
    assign data_o[2] = (mux2 & data_i[2]);
    assign data_o[1] = (mux1 & data_i[1]);
    assign data_o[0] = (mux0 & data_i[0]);
endmodule


module LOD(
    input [7:0] A,
    output zero_o,
    output [7:0] O
    );

    wire [7:0] z;
    wire [1:0] select;
    wire [1:0] zdet;

    LOD4 lod4_1 (
        .data_i(A[7:4]), 
        .data_o(z[7:4])
    );

    LOD4 lod4_0 (
        .data_i(A[3:0]), 
        .data_o(z[3:0])
    );

    LOD4 lod4_middle (
        .data_i({2'b00, zdet}),  // Expand zdet to 4-bit
        .data_o(select) // Expand select to match 4-bit output
    );

    assign zdet[1] = A[7] | A[6] | A[5] | A[4];
    assign zdet[0] = A[3] | A[2] | A[1] | A[0];
    assign zero_o = ~(zdet[1] | zdet[0]);

    Muxes2in1Array4 Inst_MUX214_1 (
        .data_i(z[7:4]), 
        .select_i(select[1]), 
        .data_o(O[7:4])
    );

    Muxes2in1Array4 Inst_MUX214_0 (
        .data_i(z[3:0]), 
        .select_i(select[0]), 
        .data_o(O[3:0])
    );

endmodule

mitchell/NOD/LOD_tb.v
`timescale 1ns / 1ps

module LOD_tb;
    
    reg [7:0] A;
    wire [7:0] O;
    wire zero_o;
    
    // Instantiate the LOD module
    LOD uut (
        .A(A),
        .zero_o(zero_o),
        .O(O)
    );
    
    initial begin
        // Dump waves for GTKWave
        $dumpfile("LOD_tb.vcd");
        $dumpvars(0, LOD_tb);
        
        // Monitor signals
        $monitor("Time=%0t A=%b O=%b", $time, A, O);
        
        // Apply test vectors
        A = 8'b00000000; #10; // Test case 1: All zeros
        A = 8'b00000001; #10; // Test case 2: Single 1 at LSB
        A = 8'b00000011; #10; // Test case 3: Single 1 at bit 1
        A = 8'b00000111; #10; // Test case 4: First three bits high
        A = 8'b01101100; #10; // Test case 5: Random middle bits
        A = 8'b10101010; #10; // Test case 6: Alternating bits
        A = 8'b11111111; #10; // Test case 7: All ones
        A = 8'b10000000; #10;
        A = 8'd73; #10 // Test case 8: Single 1 at MSB
        
        // End simulation
        $finish;
    end
    
endmodule

mitchell/NOD/LOD_tb.vcd
$date
	Sun Mar 16 12:08:15 2025
$end
$version
	Icarus Verilog
$end
$timescale
	1ps
$end
$scope module LOD_tb $end
$var wire 1 ! zero_o $end
$var wire 8 " O [7:0] $end
$var reg 8 # A [7:0] $end
$scope module uut $end
$var wire 8 $ A [7:0] $end
$var wire 1 ! zero_o $end
$var wire 2 % zdet [1:0] $end
$var wire 8 & z [7:0] $end
$var wire 2 ' select [1:0] $end
$var wire 8 ( O [7:0] $end
$scope module Inst_MUX214_0 $end
$var wire 4 ) data_i [3:0] $end
$var wire 1 * select_i $end
$var wire 4 + data_o [3:0] $end
$upscope $end
$scope module Inst_MUX214_1 $end
$var wire 4 , data_i [3:0] $end
$var wire 1 - select_i $end
$var wire 4 . data_o [3:0] $end
$upscope $end
$scope module lod4_0 $end
$var wire 4 / data_i [3:0] $end
$var wire 1 0 mux2 $end
$var wire 1 1 mux1 $end
$var wire 1 2 mux0 $end
$var wire 4 3 data_o [3:0] $end
$upscope $end
$scope module lod4_1 $end
$var wire 4 4 data_i [3:0] $end
$var wire 1 5 mux2 $end
$var wire 1 6 mux1 $end
$var wire 1 7 mux0 $end
$var wire 4 8 data_o [3:0] $end
$upscope $end
$scope module lod4_middle $end
$var wire 4 9 data_i [3:0] $end
$var wire 1 : mux2 $end
$var wire 1 ; mux1 $end
$var wire 1 < mux0 $end
$var wire 4 = data_o [3:0] $end
$upscope $end
$upscope $end
$upscope $end
$enddefinitions $end
#0
$dumpvars
b0 =
1<
1;
1:
b0 9
b0 8
17
16
15
b0 4
b0 3
12
11
10
b0 /
b0 .
0-
b0 ,
b0 +
0*
b0 )
b0 (
b0 '
b0 &
b0 %
b0 $
b0 #
b0 "
1!
$end
#10000
b1 "
b1 (
b1 +
1*
0!
b1 '
b1 )
b1 =
b1 &
b1 3
b1 9
b1 %
b1 /
b1 #
b1 $
#20000
b10 "
b10 (
b10 +
b10 )
02
b10 &
b10 3
b11 /
b11 #
b11 $
#30000
b100 "
b100 (
b100 +
b100 )
01
b100 &
b100 3
b111 /
b111 #
b111 $
#40000
0*
b100 .
1-
b10 '
0<
b10 =
b100 ,
b1000000 "
b1000000 (
b0 +
06
07
b100 8
00
b1000 )
b11 9
b11 %
b1001000 &
b1000 3
b110 4
b1100 /
b1101100 #
b1101100 $
#50000
b10000000 "
b10000000 (
b1000 .
05
06
b1000 ,
b10001000 &
b1000 8
b1010 4
b1010 /
b10101010 #
b10101010 $
#60000
b1111 4
b1111 /
b11111111 #
b11111111 $
#70000
12
11
b10 9
b10 %
10
b0 )
b10000000 &
b0 3
b1000 4
b0 /
b10000000 #
b10000000 $
#80000
02
b1000000 "
b1000000 (
b100 .
01
15
b100 ,
00
b1000 )
b100 8
b1001000 &
b1000 3
b11 9
b11 %
b100 4
b1001 /
b1001001 #
b1001001 $
