ArrayMuliplier/Signed_Verilog/SignedArrayMultiplier.v
`timescale 1ns / 1ps

module signed_arrayMul(a,b,s
    );
input [3:0] a,b;
output [7:0] s;

wire c1,c2,c3,c4,c5,c6,c7,c8,c9,c10,c11;
wire s1,s2,s3,s4,s5,s6;
wire p00,p10,p20,p30,p01,p11,p21,p31,p02,p12,p22,p32,p03,p13,p23,p33;

assign p00 = a[0] & b[0];  assign p01 = a[0] & b[1];
assign p10 = a[1] & b[0];  assign p11 = a[1] & b[1];
assign p20 = a[2] & b[0];  assign p21 = a[2] & b[1];
assign p30 = a[3] & b[0];  assign p31 = a[3] & b[1];

assign p02 = a[0] & b[2];  assign p03 = a[0] & b[3];
assign p12 = a[1] & b[2];  assign p13 = a[1] & b[3];
assign p22 = a[2] & b[2];  assign p23 = a[2] & b[3];
assign p32 = a[3] & b[2];  assign p33 = a[3] & b[3];

assign s[0] = p00;

fa m1(p10,1'b0,p01,s[1],c1);
fa m2(p20,1'b0,p11,s1,c2);
SB1 m3(p30,1'b0,p21,s2,c3);

fa m12(s1,c1,p02,s[2],c4);
SB1 m4(s2,c2,p12,s3,c5);
SB1 m5(p31,c3,p22,s4,c6);

SB2 m6(s3,c4,p03,s[3],c7);
SB2 m7(s4,c5,p13,s5,c8);
SB2 m8(p32,c6,p23,s6,c9);

SB1 m9(s5,c7,1'b0,s[4],c10);
SB1 m10(s6,c8,c10,s[5],c11);
SB1 m11(p33,c9,c11,s[6],s[7]);
endmodule

module SB2(x,z,y,s,c
    );
input x,y,z;
output s,c;
wire [1:0] s1;
//assign s1 = ( y -x - z);
//assign s = s1 % 2;
//assign s = (~x & ~y & z) + (~x & y & ~z) + (x & ~y & ~z) + (x & y & z);
assign s = x ^ y ^ z;
//assign c = (s1 + s)>>1;
assign c = (x & y) + (y & ~z) + (~z & x);
endmodule

module SB1(z,y,x,s,c
    );
input x,y,z;
output s,c;
wire [1:0] s1;
//assign s1 = ( y -x - z);
//assign s = s1 % 2;
//assign s = (~x & ~y & z) + (~x & y & ~z) + (x & ~y & ~z) + (x & y & z);
assign s = x ^ y ^ z;
//assign c = (s1 + s)>>1;
assign c = (x & y) + (y & ~z) + (~z & x);
endmodule

ArrayMuliplier/Signed_Verilog/ha.v
`timescale 1ns / 1ps

module ha(input a, input b, output sum, output carry);
    assign sum = a ^ b;   // XOR for sum
    assign carry = a & b; // AND for carry
endmodule

ArrayMuliplier/Signed_Verilog/fa.v
`timescale 1ns / 1ps

module fa(input a, input b, input cin, output sum, output cout);
    wire s1, c1, c2;
    
    ha ha1 (.a(a), .b(b), .sum(s1), .carry(c1));
    ha ha2 (.a(s1), .b(cin), .sum(sum), .carry(c2));
    
    assign cout = c1 | c2; // Carry out
endmodule

ArrayMuliplier/Signed_Verilog/tb_SignedArrayMultiplier.v
`timescale 1ns/1ps

module tb_signed_arrayMul;

  // Inputs and outputs
  reg  [3:0] a, b;
  wire [7:0] s;

  // Instantiate the design under test
  signed_arrayMul uut (
    .a(a),
    .b(b),
    .s(s)
  );

  // Dump waveforms for viewing (optional)
  initial begin
    $dumpfile("signed_arrayMul_wave.vcd");
    $dumpvars(0, tb_signed_arrayMul);
  end

  // Task to apply a test vector and check the result
  task test_vector;
    input [3:0] a_in, b_in;
    input [7:0] expected;
    begin
      a = a_in;
      b = b_in;
      #10; // wait for outputs to settle

      // Display results in a structured table format
      if (s !== expected)
        $display("| %8t |   %4b (%3d) |   %4b (%3d) |  %8b (%3d) | %8b (%3d) | ERROR", 
                  $time, a_in, $signed(a_in), b_in, $signed(b_in), s, $signed(s), expected, $signed(expected));
      else
        $display("| %8t |   %4b (%3d) |   %4b (%3d) |  %8b (%3d) | %8b (%3d) | PASS",
                  $time, a_in, $signed(a_in), b_in, $signed(b_in), s, $signed(s), expected, $signed(expected));
    end
  endtask

  // Apply a series of test vectors
  initial begin
    $display("Starting simulation...\n");

    // Display header
    $display("------------------------------------------------------------------");
    $display("| Time (ns) |   a (bin)  |   b (bin)  |  s (output)  | Expected   |");
    $display("------------------------------------------------------------------");

    // Test cases
    test_vector(4'b0000, 4'b0000, 8'b00000000); //  0 *  0 =  0
    test_vector(4'b0001, 4'b0001, 8'b00000001); //  1 *  1 =  1
    test_vector(4'b0010, 4'b0010, 8'b00000100); //  2 *  2 =  4
    test_vector(4'b0100, 4'b0011, 8'b00001100); //  4 *  3 = 12
    test_vector(4'b1010, 4'b0101, 8'b11100010); // -6 *  5 = -30
    test_vector(4'b1111, 4'b1111, 8'b00000001); // -1 * -1 =  1
    test_vector(4'b1100, 4'b1100, 8'b00010000); // -4 * -4 = 16
    test_vector(4'b0111, 4'b0111, 8'b00110001); //  7 *  7 = 49
    test_vector(4'b1001, 4'b0011, 8'b11101011); // -7 *  3 = -21

    // End simulation
    $display("------------------------------------------------------------------");
    $display("Simulation complete.");
    $finish;
  end

endmodule

ArrayMuliplier/Signed_Verilog/signed_arrayMul_wave.vcd
$date
	Sat Mar 15 09:07:32 2025
$end
$version
	Icarus Verilog
$end
$timescale
	1ps
$end
$scope module tb_signed_arrayMul $end
$var wire 8 ! s [7:0] $end
$var reg 4 " a [3:0] $end
$var reg 4 # b [3:0] $end
$scope module uut $end
$var wire 4 $ a [3:0] $end
$var wire 4 % b [3:0] $end
$var wire 1 & p00 $end
$var wire 1 ' p01 $end
$var wire 1 ( p02 $end
$var wire 1 ) p03 $end
$var wire 1 * p10 $end
$var wire 1 + p11 $end
$var wire 1 , p12 $end
$var wire 1 - p13 $end
$var wire 1 . p20 $end
$var wire 1 / p21 $end
$var wire 1 0 p22 $end
$var wire 1 1 p23 $end
$var wire 1 2 p30 $end
$var wire 1 3 p31 $end
$var wire 1 4 p32 $end
$var wire 1 5 p33 $end
$var wire 1 6 s6 $end
$var wire 1 7 s5 $end
$var wire 1 8 s4 $end
$var wire 1 9 s3 $end
$var wire 1 : s2 $end
$var wire 1 ; s1 $end
$var wire 8 < s [7:0] $end
$var wire 1 = c9 $end
$var wire 1 > c8 $end
$var wire 1 ? c7 $end
$var wire 1 @ c6 $end
$var wire 1 A c5 $end
$var wire 1 B c4 $end
$var wire 1 C c3 $end
$var wire 1 D c2 $end
$var wire 1 E c11 $end
$var wire 1 F c10 $end
$var wire 1 G c1 $end
$scope module m1 $end
$var wire 1 * a $end
$var wire 1 H b $end
$var wire 1 ' cin $end
$var wire 1 G cout $end
$var wire 1 I sum $end
$var wire 1 J s1 $end
$var wire 1 K c2 $end
$var wire 1 L c1 $end
$scope module ha1 $end
$var wire 1 * a $end
$var wire 1 H b $end
$var wire 1 L carry $end
$var wire 1 J sum $end
$upscope $end
$scope module ha2 $end
$var wire 1 J a $end
$var wire 1 ' b $end
$var wire 1 K carry $end
$var wire 1 I sum $end
$upscope $end
$upscope $end
$scope module m10 $end
$var wire 1 M s $end
$var wire 1 6 z $end
$var wire 1 > y $end
$var wire 1 F x $end
$var wire 1 E c $end
$upscope $end
$scope module m11 $end
$var wire 1 N s $end
$var wire 1 E x $end
$var wire 1 5 z $end
$var wire 1 = y $end
$var wire 1 O c $end
$upscope $end
$scope module m12 $end
$var wire 1 G b $end
$var wire 1 ( cin $end
$var wire 1 B cout $end
$var wire 1 P sum $end
$var wire 1 Q s1 $end
$var wire 1 R c2 $end
$var wire 1 S c1 $end
$var wire 1 ; a $end
$scope module ha1 $end
$var wire 1 G b $end
$var wire 1 S carry $end
$var wire 1 Q sum $end
$var wire 1 ; a $end
$upscope $end
$scope module ha2 $end
$var wire 1 Q a $end
$var wire 1 ( b $end
$var wire 1 R carry $end
$var wire 1 P sum $end
$upscope $end
$upscope $end
$scope module m2 $end
$var wire 1 . a $end
$var wire 1 T b $end
$var wire 1 + cin $end
$var wire 1 D cout $end
$var wire 1 ; sum $end
$var wire 1 U s1 $end
$var wire 1 V c2 $end
$var wire 1 W c1 $end
$scope module ha1 $end
$var wire 1 . a $end
$var wire 1 T b $end
$var wire 1 W carry $end
$var wire 1 U sum $end
$upscope $end
$scope module ha2 $end
$var wire 1 U a $end
$var wire 1 + b $end
$var wire 1 V carry $end
$var wire 1 ; sum $end
$upscope $end
$upscope $end
$scope module m3 $end
$var wire 1 : s $end
$var wire 1 / x $end
$var wire 1 X y $end
$var wire 1 2 z $end
$var wire 1 C c $end
$upscope $end
$scope module m4 $end
$var wire 1 9 s $end
$var wire 1 , x $end
$var wire 1 D y $end
$var wire 1 : z $end
$var wire 1 A c $end
$upscope $end
$scope module m5 $end
$var wire 1 8 s $end
$var wire 1 0 x $end
$var wire 1 C y $end
$var wire 1 3 z $end
$var wire 1 @ c $end
$upscope $end
$scope module m6 $end
$var wire 1 Y s $end
$var wire 1 9 x $end
$var wire 1 ) y $end
$var wire 1 B z $end
$var wire 1 ? c $end
$upscope $end
$scope module m7 $end
$var wire 1 7 s $end
$var wire 1 8 x $end
$var wire 1 - y $end
$var wire 1 A z $end
$var wire 1 > c $end
$upscope $end
$scope module m8 $end
$var wire 1 6 s $end
$var wire 1 4 x $end
$var wire 1 1 y $end
$var wire 1 @ z $end
$var wire 1 = c $end
$upscope $end
$scope module m9 $end
$var wire 1 Z s $end
$var wire 1 [ x $end
$var wire 1 ? y $end
$var wire 1 7 z $end
$var wire 1 F c $end
$upscope $end
$upscope $end
$scope task test_vector $end
$var reg 4 \ a_in [3:0] $end
$var reg 4 ] b_in [3:0] $end
$var reg 8 ^ expected [7:0] $end
$upscope $end
$upscope $end
$enddefinitions $end
$comment Show the parameter values. $end
$dumpall
$end
#0
$dumpvars
b0 ^
b0 ]
b0 \
0[
0Z
0Y
0X
0W
0V
0U
0T
0S
0R
0Q
0P
0O
0N
0M
0L
0K
0J
0I
0H
0G
0F
0E
0D
0C
0B
0A
0@
0?
0>
0=
b0 <
0;
0:
09
08
07
06
05
04
03
02
01
00
0/
0.
0-
0,
0+
0*
0)
0(
0'
0&
b0 %
b0 $
b0 #
b0 "
b0 !
$end
#10000
b1 !
b1 <
1&
b1 #
b1 %
b1 "
b1 $
b1 ^
b1 ]
b1 \
#20000
1P
1Q
1;
b100 !
b100 <
0&
1+
b10 #
b10 %
b10 "
b10 $
b100 ^
b10 ]
b10 \
#30000
0N
0O
0E
1Y
0F
17
1?
1>
b1100 !
b1100 <
0M
19
18
16
1:
1@
1U
1C
0+
1.
1/
b11 #
b11 %
b100 "
b100 $
b1100 ^
b11 ]
b100 \
#40000
1N
0Y
0Z
1O
0P
0?
0>
1=
07
0E
0Q
09
08
0A
1M
b11100010 !
b11100010 <
1I
0;
0@
16
1J
0U
0C
1:
1*
0.
0/
12
1,
14
b101 #
b101 %
b1010 "
b1010 $
b11100010 ^
b101 ]
b1010 \
#50000
0Z
1B
0M
1R
1A
06
1Q
09
1D
07
0E
1G
0:
0Y
0F
0O
1V
0>
0N
0I
1K
1U
0P
0?
0@
1=
1+
13
1-
15
b1 !
b1 <
1&
1'
1.
1/
1(
1)
10
11
b1111 #
b1111 %
b1111 "
b1111 $
b1 ^
b1111 ]
b1111 \
#60000
1>
0M
1=
16
1Z
1@
0G
0S
0Q
0D
0B
0Y
17
0U
0:
18
0K
0J
0;
0V
0P
0R
0A
0.
0/
02
03
b10000 !
b10000 <
0&
0'
0*
0+
0(
0)
0,
0-
b1100 #
b1100 %
b1100 "
b1100 $
b10000 ^
b1100 ]
b1100 \
#70000
1M
1B
0Y
0F
1D
08
1R
0?
1Z
0>
1V
1:
1@
1G
1Q
19
17
1U
1C
1K
1J
0;
0P
1A
0=
0N
1.
1/
01
b110001 !
b110001 <
1&
1'
1*
1+
1(
1,
04
05
b111 #
b111 %
b111 "
b111 $
b110001 ^
b111 ]
b111 \
#80000
1N
1O
1?
1E
0Q
1>
1M
1Y
0G
19
18
06
0Z
0B
1I
0K
0D
17
b11101011 !
b11101011 <
0P
0R
0J
0V
0U
0C
1:
0A
0@
0(
0*
0+
0.
0/
12
13
0,
00
b11 #
b11 %
b1001 "
b1001 $
b11101011 ^
b11 ]
b1001 \
