alm/alm_soa_3.v
module Barrel8L(
    input [7:0] data_i,
    input [2:0] shift_i,
    output reg [7:0] data_o
    );	 
 
   always @*
      case (shift_i)
         3'd0: data_o = data_i;
         3'd1: data_o = data_i << 1;
         3'd2: data_o = data_i << 2;
         3'd3: data_o = data_i << 3;
         3'd4: data_o = data_i << 4;
         3'd5: data_o = data_i << 5;
         3'd6: data_o = data_i << 6;
         3'd7: data_o = data_i << 7;
      endcase

endmodule


module Barrel8R (
    input [7:0] data_i,
	input [2:0] shift_i,
	output reg [7:0] data_o
    );

	always @*
      case (shift_i)
         3'd0: data_o = data_i;
         3'd1: data_o = data_i >> 1;
         3'd2: data_o = data_i >> 2;
         3'd3: data_o = data_i >> 3;
         3'd4: data_o = data_i >> 4;
         3'd5: data_o = data_i >> 5;
         3'd6: data_o = data_i >> 6;
         3'd7: data_o = data_i >> 7;
      endcase
endmodule


module Barrel16L(
    input [15:0] data_i,
    input [3:0] shift_i,
    output reg [15:0] data_o
    );	 
 
   always @*
      case (shift_i)
         4'd0: data_o = data_i;
         4'd1: data_o = data_i << 1;
         4'd2: data_o = data_i << 2;
         4'd3: data_o = data_i << 3;
         4'd4: data_o = data_i << 4;
         4'd5: data_o = data_i << 5;
         4'd6: data_o = data_i << 6;
         4'd7: data_o = data_i << 7;
         4'd8: data_o = data_i<<8;
         4'd9: data_o = data_i << 9;
         4'd10: data_o = data_i << 10;
         4'd11: data_o = data_i << 11;
         4'd12: data_o = data_i << 12;
         4'd13: data_o = data_i << 13;
         4'd14: data_o = data_i << 14;
         4'd15: data_o = data_i << 15;
      endcase

endmodule


module carry_lookahead_inc(
    input [2:0] i_add1,
    output [3:0] o_result
);
    
    wire [2:0] carry;
    wire [2:0] sum;
    
    // Generate carry signals using lookahead logic
    assign carry[0] = 1'b1; // Incrementing, so initial carry-in is 1
    assign carry[1] = (i_add1[0] & carry[0]);
    assign carry[2] = (i_add1[1] & carry[1]);
    
    // Compute sum bits
    assign sum[0] = i_add1[0] ^ carry[0];
    assign sum[1] = i_add1[1] ^ carry[1];
    assign sum[2] = i_add1[2] ^ carry[2];

    // Output the incremented result
    assign o_result = {carry[2],sum};
    
endmodule


module AntiLog(
    input  [10:0] data_i,   // [10] = lr flag, [9:7] = exponent, [6:0] = fraction
    output [15:0] data_o    // 16-bit approximate product output
);

    // -------------------------------
    // Left Barrel Shift Branch (for lr = 1)
    // -------------------------------
    wire [15:0] l1_in;
    assign l1_in = {8'b0, 1'b1, data_i[6:0]};  // 8 + 1 + 7 = 16 bits

    wire [2:0] k_enc;
    wire [3:0] k_enc_inc;
    assign k_enc = {1'b0,data_i[9:7]};  // Extract exponent
    // assign k_enc_inc = k_enc + 3'b001;  // Simple increment

    carry_lookahead_inc inc(
        .i_add1(k_enc),
        .o_result(k_enc_inc)
    );

    wire [15:0] l1_out;
    Barrel16L L1shift (
        .data_i(l1_in),
        .shift_i(k_enc_inc),
        .data_o(l1_out)
    );

    // -------------------------------
    // Right Barrel Shift Branch (for lr = 0)
    // -------------------------------
    wire [7:0] r_in;
    assign r_in = {1'b1, data_i[6:0]};  // 1 + 7 = 8 bits

    wire [2:0] enc;
    assign enc = ~data_i[9:7];  // Compute correct right-shift amount

    wire [7:0] r_out;
    Barrel8R Rshift (
        .data_i(r_in),
        .shift_i(enc),
        .data_o(r_out)
    );
    
    // assign data_o = data_i[10] ? l1_out : {8'd0, r_out};  // Full selection
    wire [7:0] data_msb,data_lsb;
    assign data_msb= {8{data_i[10]}}&l1_out[15:8];
    assign data_lsb=data_i[10] ? l1_out[7:0] : r_out; 
    assign data_o = {data_msb,data_lsb};  // Full selection

endmodule

module PEncoder (
    input [7:0] A,
    output [2:0] out
);

    wire temp1, temp2, temp3, temp4, temp5;

    assign temp1 = A[1] || A[3];
    assign temp2 = A[2] || A[3];
    assign temp3 = A[4] || A[5];
    assign temp4 = A[6] || A[7];
    assign temp5 = A[5] || A[7];

    assign out[0] = temp1 || temp5;
    assign out[1] = temp2 || temp4;
    assign out[2] = temp3 || temp4;
    
endmodule


module Muxes2in1Array4(
    input [3:0] data_i,
    input select_i,
    output [3:0] data_o
    );

    assign data_o = select_i ? data_i : 4'b0000;

endmodule


module LOD4(
    input [3:0] data_i,
    output [3:0] data_o
    ); 
    wire mux0;
    wire mux1;
    wire mux2;
    
    assign mux2 = data_i[3] ? 1'b0 : 1'b1;
    assign mux1 = data_i[2] ? 1'b0 : mux2;
    assign mux0 = data_i[1] ? 1'b0 : mux1;
    
    assign data_o[3] = data_i[3];
    assign data_o[2] = (mux2 & data_i[2]);
    assign data_o[1] = (mux1 & data_i[1]);
    assign data_o[0] = (mux0 & data_i[0]);
endmodule


module LOD2(
    input [1:0] data_i,
    output [1:0] data_o
    ); 
    wire mux0;

    assign mux0 = data_i[1] ? 1'b0 : 1'b1;

    assign data_o[1] = data_i[1];
    assign data_o[0] = (mux0 & data_i[0]);
endmodule


module LOD(
    input [7:0] A,
    output zero_o,
    output [7:0] O
    );

    wire [7:0] z;
    wire [1:0] select;
    wire [1:0] zdet;

    LOD4 lod4_1 (
        .data_i(A[7:4]), 
        .data_o(z[7:4])
    );

    LOD4 lod4_0 (
        .data_i(A[3:0]), 
        .data_o(z[3:0])
    );

    LOD2 lod4_middle (
        .data_i( zdet),  // Expand zdet to 4-bit
        .data_o(select) // Expand select to match 4-bit output
    );

    assign zdet[1] = A[7] | A[6] | A[5] | A[4];
    assign zdet[0] = A[3] | A[2] | A[1] | A[0];
    assign zero_o = ~(zdet[1] | zdet[0]);

    Muxes2in1Array4 Inst_MUX214_1 (
        .data_i(z[7:4]), 
        .select_i(select[1]), 
        .data_o(O[7:4])
    );

    Muxes2in1Array4 Inst_MUX214_0 (
        .data_i(z[3:0]), 
        .select_i(select[0]), 
        .data_o(O[3:0])
    );

endmodule


module ALM_SOA(
    input [8:0] x,
    input [8:0] y,
    output [16:0] p
    );

    wire [7:0] A,B;
    assign A=x[7:0];
    assign B=y[7:0];

    wire [7:0] LODa,LODb;
    wire [2:0] kA,kB;
    wire zeroA,zeroB;

    LOD lodA(A,zeroA,LODa);
    LOD lodB(B,zeroB,LODb);

    PEncoder peA(LODa,kA);
    PEncoder peB(LODb,kB);

    wire [2:0] kA_inv;
	wire [7:0] barrelA;
	
	assign kA_inv = ~kA;
	
	Barrel8L BShiftA (
		.data_i(A),
		.shift_i(kA_inv),
		.data_o(barrelA)
 	 ); 

    wire [2:0] kB_inv;
	wire [7:0] barrelB;

	assign kB_inv = ~kB;
	
	Barrel8L BShiftB (
		.data_i(B),
		.shift_i(kB_inv),
		.data_o(barrelB)
 	 );

    wire [6:0] op1,op2;
    wire [10:0] L;

    assign op1={kA,barrelA[6:3]};
    assign op2={kB,barrelB[6:3]};

    assign c_in = A[2] & B[2];

    assign L[10:3] = op1 + op2 + c_in;
    assign L[2:0] = {3{1'b1}};

    wire [15:0] tmp_out; 

	AntiLog anti_log(
		.data_i(L),
		.data_o(tmp_out)
	);
	
	wire prod_sign; 
	wire [15:0] tmp_sign;
	
	assign prod_sign = x[8] ^ y[8];
	assign tmp_sign = {17{prod_sign}} ^ tmp_out;
	
	// is zero 
	wire not_zero;
	assign not_zero = (~zeroA | x[8] | x[0]) & (~zeroB | y[8] | y[0]);
	
	assign p = not_zero ? tmp_sign : 16'b0;

endmodule

alm/alm_soa_tb.v
`timescale 1ns / 1ps

module ALM_SOA_tb;

    // Inputs (8-bit unsigned)
    reg [8:0] x, y;
    
    // Outputs
    wire [16:0] p;
    // wire [7:0] LODa,LODb,A,B;
    // wire [2:0] kA, kB;
    // wire [10:0] op1, op2, L;
    // wire [15:0] tmp_out;
    // wire prod_sign;

    // Intermediate signals for signed values
    // integer signed_in1, signed_in2, signed_product;
    reg [16:0] signed_product;
    // Instantiate the ILM module
    ALM_SOA uut (
        .x(x), 
        .y(y), 
        .p(p)
        // .prod_sign(prod_sign),
        // .tmp_out(tmp_out),

        // .A(A),
        // .B(B)
        // .LODa(LODa),
        // .LODb(LODb),
        // .kA(kA), 
        // .kB(kB),
        // .op1(op1),
        // .op2(op2),
        // .L(L),
        // .tmp_out(tmp_out)
    );
    
    // Test cases
    initial begin
        // Enable waveform dumping for GTKWave
        $dumpfile("ALM_SOA_tb.vcd");  // Name of the VCD file
        $dumpvars(0, uut);      // Dump all variables in this module

        // Monitor output
        $monitor("Time = %0t | x = %b (%d), y = %b (%d) | Product = %b (%d)", 
                 $time, x,x, y,y , p,signed_product);
        
        // Apply test cases (8-bit unsigned numbers)
                // Test Case 1: 5 * 3
        x = 9'd5;  y = 9'd3;  #10;
        x = 9'd15; y = 9'd5;  #10;
        x = 9'd20; y = 9'd4;  #10;
        x = 9'd8;  y = 9'd2;  #10;
        x = 9'd50; y = 9'd7;  #10;
        x = 9'd25; y = 9'd6;  #10;
        x = 9'd129; y = 9'd65;  #10;
        x = 9'd0;  y = 9'd18; #10;
        x = 9'd1;  y = 9'd1;  #10;
        x = 9'd255; y = 9'd255; #10;
        x= 9'd30; y=9'd68; #10

        // x = -9'd5;  y = 9'd3;  #10;
        // x = 9'd15; y = -9'd5;  #10;
        // x = -9'd20; y = -9'd4;  #10;
        // x = -9'd8;  y = 9'd2;  #10;
        // x = 9'd50; y = -9'd7;  #10;
        // x = -9'd25; y = -9'd6;  #10;
        // x = -9'd129; y = 9'd65;  #10;
        // x = 9'd0;  y = -9'd18; #10;
        // x = -9'd1;  y = -9'd1;  #10;
        // x = -9'd255; y = 9'd255; #10;

        // End simulation
        $finish;
    end
    always @(*) begin
        signed_product=({17{p[16]}}^p)+p[16];
    end   
endmodule

alm/ALM_SOA_tb.vcd
$date
	Wed Apr 16 16:08:12 2025
$end
$version
	Icarus Verilog
$end
$timescale
	1ps
$end
$scope module ALM_SOA_tb $end
$scope module uut $end
$var wire 1 ! c_in $end
$var wire 3 " kA_inv [2:0] $end
$var wire 3 # kB_inv [2:0] $end
$var wire 1 $ not_zero $end
$var wire 1 % prod_sign $end
$var wire 9 & x [8:0] $end
$var wire 9 ' y [8:0] $end
$var wire 1 ( zeroB $end
$var wire 1 ) zeroA $end
$var wire 16 * tmp_sign [15:0] $end
$var wire 16 + tmp_out [15:0] $end
$var wire 17 , p [16:0] $end
$var wire 7 - op2 [6:0] $end
$var wire 7 . op1 [6:0] $end
$var wire 3 / kB [2:0] $end
$var wire 3 0 kA [2:0] $end
$var wire 8 1 barrelB [7:0] $end
$var wire 8 2 barrelA [7:0] $end
$var wire 8 3 LODb [7:0] $end
$var wire 8 4 LODa [7:0] $end
$var wire 11 5 L [10:0] $end
$var wire 8 6 B [7:0] $end
$var wire 8 7 A [7:0] $end
$scope module BShiftA $end
$var wire 8 8 data_i [7:0] $end
$var wire 3 9 shift_i [2:0] $end
$var reg 8 : data_o [7:0] $end
$upscope $end
$scope module BShiftB $end
$var wire 8 ; data_i [7:0] $end
$var wire 3 < shift_i [2:0] $end
$var reg 8 = data_o [7:0] $end
$upscope $end
$scope module anti_log $end
$var wire 11 > data_i [10:0] $end
$var wire 8 ? data_msb [7:0] $end
$var wire 3 @ enc [2:0] $end
$var wire 8 A r_out [7:0] $end
$var wire 8 B r_in [7:0] $end
$var wire 16 C l1_out [15:0] $end
$var wire 16 D l1_in [15:0] $end
$var wire 4 E k_enc_inc [3:0] $end
$var wire 3 F k_enc [2:0] $end
$var wire 16 G data_o [15:0] $end
$var wire 8 H data_lsb [7:0] $end
$scope module L1shift $end
$var wire 16 I data_i [15:0] $end
$var wire 4 J shift_i [3:0] $end
$var reg 16 K data_o [15:0] $end
$upscope $end
$scope module Rshift $end
$var wire 8 L data_i [7:0] $end
$var wire 3 M shift_i [2:0] $end
$var reg 8 N data_o [7:0] $end
$upscope $end
$scope module inc $end
$var wire 3 O i_add1 [2:0] $end
$var wire 3 P sum [2:0] $end
$var wire 4 Q o_result [3:0] $end
$var wire 3 R carry [2:0] $end
$upscope $end
$upscope $end
$scope module lodA $end
$var wire 8 S A [7:0] $end
$var wire 1 ) zero_o $end
$var wire 2 T zdet [1:0] $end
$var wire 8 U z [7:0] $end
$var wire 2 V select [1:0] $end
$var wire 8 W O [7:0] $end
$scope module Inst_MUX214_0 $end
$var wire 4 X data_i [3:0] $end
$var wire 1 Y select_i $end
$var wire 4 Z data_o [3:0] $end
$upscope $end
$scope module Inst_MUX214_1 $end
$var wire 4 [ data_i [3:0] $end
$var wire 1 \ select_i $end
$var wire 4 ] data_o [3:0] $end
$upscope $end
$scope module lod4_0 $end
$var wire 4 ^ data_i [3:0] $end
$var wire 1 _ mux2 $end
$var wire 1 ` mux1 $end
$var wire 1 a mux0 $end
$var wire 4 b data_o [3:0] $end
$upscope $end
$scope module lod4_1 $end
$var wire 4 c data_i [3:0] $end
$var wire 1 d mux2 $end
$var wire 1 e mux1 $end
$var wire 1 f mux0 $end
$var wire 4 g data_o [3:0] $end
$upscope $end
$scope module lod4_middle $end
$var wire 2 h data_i [1:0] $end
$var wire 1 i mux0 $end
$var wire 2 j data_o [1:0] $end
$upscope $end
$upscope $end
$scope module lodB $end
$var wire 8 k A [7:0] $end
$var wire 1 ( zero_o $end
$var wire 2 l zdet [1:0] $end
$var wire 8 m z [7:0] $end
$var wire 2 n select [1:0] $end
$var wire 8 o O [7:0] $end
$scope module Inst_MUX214_0 $end
$var wire 4 p data_i [3:0] $end
$var wire 1 q select_i $end
$var wire 4 r data_o [3:0] $end
$upscope $end
$scope module Inst_MUX214_1 $end
$var wire 4 s data_i [3:0] $end
$var wire 1 t select_i $end
$var wire 4 u data_o [3:0] $end
$upscope $end
$scope module lod4_0 $end
$var wire 4 v data_i [3:0] $end
$var wire 1 w mux2 $end
$var wire 1 x mux1 $end
$var wire 1 y mux0 $end
$var wire 4 z data_o [3:0] $end
$upscope $end
$scope module lod4_1 $end
$var wire 4 { data_i [3:0] $end
$var wire 1 | mux2 $end
$var wire 1 } mux1 $end
$var wire 1 ~ mux0 $end
$var wire 4 !" data_o [3:0] $end
$upscope $end
$scope module lod4_middle $end
$var wire 2 "" data_i [1:0] $end
$var wire 1 #" mux0 $end
$var wire 2 $" data_o [1:0] $end
$upscope $end
$upscope $end
$scope module peA $end
$var wire 8 %" A [7:0] $end
$var wire 1 &" temp1 $end
$var wire 1 '" temp2 $end
$var wire 1 (" temp3 $end
$var wire 1 )" temp4 $end
$var wire 1 *" temp5 $end
$var wire 3 +" out [2:0] $end
$upscope $end
$scope module peB $end
$var wire 8 ," A [7:0] $end
$var wire 1 -" temp1 $end
$var wire 1 ." temp2 $end
$var wire 1 /" temp3 $end
$var wire 1 0" temp4 $end
$var wire 1 1" temp5 $end
$var wire 3 2" out [2:0] $end
$upscope $end
$upscope $end
$upscope $end
$enddefinitions $end
#0
$dumpvars
b1 2"
01"
00"
0/"
0."
1-"
b10 ,"
b10 +"
0*"
0)"
0("
1'"
0&"
b100 %"
b1 $"
1#"
b1 ""
b0 !"
1~
1}
1|
b0 {
b10 z
0y
1x
1w
b11 v
b0 u
0t
b0 s
b10 r
1q
b10 p
b10 o
b1 n
b10 m
b1 l
b11 k
b1 j
1i
b1 h
b0 g
1f
1e
1d
b0 c
b100 b
0a
0`
1_
b101 ^
b0 ]
0\
b0 [
b100 Z
1Y
b100 X
b100 W
b1 V
b100 U
b1 T
b101 S
b111 R
b1100 Q
b100 P
b11 O
b1110 N
b100 M
b11100111 L
b111000000000000 K
b1100 J
b11100111 I
b1110 H
b1110 G
b11 F
b1100 E
b11100111 D
b111000000000000 C
b11100111 B
b1110 A
b100 @
b0 ?
b111100111 >
b11000000 =
b110 <
b11 ;
b10100000 :
b101 9
b101 8
b101 7
b11 6
b111100111 5
b100 4
b10 3
b10100000 2
b11000000 1
b10 0
b1 /
b100100 .
b11000 -
b1110 ,
b1110 +
b1110 *
0)
0(
b11 '
b101 &
0%
1$
b110 #
b101 "
0!
$end
#10000
b101 #
b101 <
b100100 -
b10 /
b10 2"
b1001111 ,
b100 "
b100 9
0-"
1."
b1001111 *
b11 0
b11 +"
b1 R
b111 E
b111 J
b111 Q
b111 P
1&"
b100 3
b100 o
b100 ,"
b100 r
b1001111 +
b1001111 G
b1001111 H
b100 p
b100111110000000 C
b100111110000000 K
b110 F
b110 O
b1001111 A
b1001111 N
b1 @
b1 M
b1000 4
b1000 W
b1000 %"
b1000 Z
0x
0y
b100 m
b100 z
b10011111 D
b10011111 I
b10011111 B
b10011111 L
0_
b1000 X
1!
b1100011111 5
b1100011111 >
b111110 .
b1000 U
b1000 b
b10100000 1
b10100000 =
b101 v
b11110000 2
b11110000 :
b1111 ^
b101 6
b101 ;
b101 k
b1111 7
b1111 8
b1111 S
b101 '
b1111 &
#20000
b1010111 ,
b11 "
b11 9
b1010111 *
b100 0
b100 +"
1("
b1 R
b111 E
b111 J
b111 Q
b111 P
0&"
0'"
0Y
b1010111 +
b1010111 G
b1010111 H
b1 ]
b101011110000000 C
b101011110000000 K
b110 F
b110 O
b1010111 A
b1010111 N
b1 @
b1 M
b1 [
b10000 4
b10000 W
b10000 %"
b0 Z
0i
1\
b10101111 D
b10101111 I
b10101111 B
b10101111 L
b1 g
1_
b100 X
b10 V
b10 j
b100000 -
b1100101111 5
b1100101111 >
b1000100 .
b10100 U
b100 b
b11 T
b11 h
b10000000 1
b10000000 =
b100 v
b10100000 2
b10100000 :
b1 c
b100 ^
b100 6
b100 ;
b100 k
b10100 7
b10100 8
b10100 S
b100 '
b10100 &
#30000
b110 #
b110 <
1&"
1'"
b100 "
b100 9
1-"
b1 /
b1 2"
b10000 ,
b11 0
b11 +"
0."
b10000 *
b1000 Z
0("
b1 R
b101 E
b101 J
b101 Q
b101 P
1Y
b10 3
b10 o
b10 ,"
b10 r
b10000 +
b10000 G
b10000 H
b1000 4
b1000 W
b1000 %"
b0 ]
b100 F
b100 O
b11 @
b11 M
b10 p
b1000011100000 C
b1000011100000 K
b10000 A
b10000 N
b0 [
0a
1i
0\
1x
b10 m
b10 z
b10000111 D
b10000111 I
b10000111 B
b10000111 L
b0 g
0_
0`
b1000 X
b1 V
b1 j
b10000 -
0!
b1000000111 5
b1000000111 >
b110000 .
b1000 U
b1000 b
b1 T
b1 h
b10000000 1
b10000000 =
b10 v
b10000000 2
b10000000 :
b0 c
b1000 ^
b10 6
b10 ;
b10 k
b1000 7
b1000 8
b1000 S
b10 '
b1000 &
#40000
b1 E
b1 J
b1 Q
b1 P
b1 ?
b101 #
b101 <
b0 F
b0 O
b111 @
b111 M
0-"
b10 /
b10 2"
b101011110 ,
b10 "
b10 9
1."
b101011110 *
b101 0
b101 +"
1("
1*"
0&"
0'"
0Y
b100 3
b100 o
b100 ,"
b100 r
b101011110 +
b101011110 G
b1011110 H
b10 ]
b100 p
b101011110 C
b101011110 K
b1 A
b1 N
b10 [
1`
b100000 4
b100000 W
b100000 %"
b0 Z
0i
1\
0x
b100 m
b100 z
b10101111 D
b10101111 I
b10101111 B
b10101111 L
0f
b10 g
1_
b10 X
b10 V
b10 j
b101100 -
b10000101111 5
b10000101111 >
b1011001 .
b100010 U
b10 b
b11 T
b11 h
b11100000 1
b11100000 =
b111 v
b11001000 2
b11001000 :
b11 c
b10 ^
b111 6
b111 ;
b111 k
b110010 7
b110010 8
b110010 S
b111 '
b110010 &
#50000
b111 R
b1000 E
b1000 J
b1000 Q
b0 P
b10001111 A
b10001111 N
b111 F
b111 O
b0 @
b0 M
b0 ?
b10001111 ,
b11 "
b11 9
b10001111 *
b100 0
b100 +"
1("
0*"
b10001111 +
b10001111 G
b10001111 H
b10000 4
b10000 W
b10000 %"
b1 ]
b1000111100000000 C
b1000111100000000 K
b1 [
0`
b10001111 D
b10001111 I
b10001111 B
b10001111 L
1f
b1 g
0_
0a
b1000 X
b101000 -
b1110001111 5
b1110001111 >
b1001001 .
b11000 U
b1000 b
b11000000 1
b11000000 =
b110 v
b11001000 2
b11001000 :
b1 c
b1001 ^
b110 6
b110 ;
b110 k
b11001 7
b11001 8
b11001 S
b110 '
b11001 &
#60000
b100001 ?
b1 #
b1 <
10"
1)"
1*"
b110 /
b110 2"
0q
b10000111000000 ,
b0 "
b0 9
0."
b100 u
b10000111000000 *
b111 0
b111 +"
0#"
1t
b11 R
b110 E
b110 J
b110 Q
b110 P
0("
0Y
b1000000 3
b1000000 o
b1000000 ,"
b0 r
b10 n
b10 $"
b10000111000000 +
b10000111000000 G
b11000000 H
0f
1a
0~
b100 s
1y
b1 p
b11 l
b11 ""
b10000111000000 C
b10000111000000 K
b101 F
b101 O
b100001 A
b100001 N
b10 @
b10 M
0e
b10000000 4
b10000000 W
b10000000 %"
b1000 ]
1`
0i
1\
0}
b100 !"
1x
b1000001 m
b1 z
b10000111 D
b10000111 I
b10000111 B
b10000111 L
0d
b1000 [
1_
b1 X
b10 V
b10 j
b1100000 -
b11010000111 5
b11010000111 >
b1110000 .
b1000 g
b10000001 U
b1 b
b11 T
b11 h
b10000010 1
b10000010 =
b100 {
b1 v
b10000001 2
b10000001 :
b1000 c
b1 ^
b1000001 6
b1000001 ;
b1000001 k
b10000001 7
b10000001 8
b10000001 S
b1000001 '
b10000001 &
#70000
b1 R
b101 E
b101 J
b101 Q
b101 P
0$
b0 ,
1/"
b11 #
b11 <
b10010 H
b100 F
b100 O
b11 @
b11 M
b10010 *
b100 /
b100 2"
b111 "
b111 9
00"
b0 .
b0 0
b0 +"
1)
b10010 +
b10010 G
b0 ?
0)"
0*"
1i
0\
b10000 3
b10000 o
b10000 ,"
b1 u
1f
b0 V
b0 j
b1001011100000 C
b1001011100000 K
b10010 A
b10010 N
1~
b1 s
b10 p
1e
b0 4
b0 W
b0 %"
b0 ]
b0 X
b10010111 D
b10010111 I
b10010111 B
b10010111 L
1}
b1 !"
0y
b10010 m
b10 z
1d
b0 [
b0 b
b1000010111 5
b1000010111 >
b1000010 -
b11 l
b11 ""
b0 U
b0 g
b0 T
b0 h
b10010000 1
b10010000 =
b1 {
b10 v
b0 2
b0 :
b0 c
b0 ^
b10010 6
b10010 ;
b10010 k
b0 7
b0 8
b0 S
b10010 '
b0 &
#80000
b1 E
b1 J
b1 Q
b1 P
b0 F
b0 O
b111 @
b111 M
b111 #
b111 <
b0 /
b0 2"
b1 *
b1 r
0/"
1q
b1 4
b1 W
b1 %"
b1 Z
b1 +
b1 G
b1 H
b1 3
b1 o
b1 ,"
b0 u
0)
1Y
b100001110 C
b100001110 K
b1 A
b1 N
b0 s
b1 p
1#"
0t
b1 X
b1 V
b1 j
b10000111 D
b10000111 I
b10000111 B
b10000111 L
b0 !"
1y
b1 m
b1 z
b1 n
b1 $"
b1 U
b1 b
b1 ,
b111 5
b111 >
b0 -
b1 l
b1 ""
b1 T
b1 h
1$
b10000000 1
b10000000 =
b0 {
b1 v
b10000000 2
b10000000 :
b1 ^
b1 6
b1 ;
b1 k
b1 7
b1 8
b1 S
b1 '
b1 &
#90000
b111 R
b1111111100000000 ,
b1111111100000000 *
b1000 E
b1000 J
b1000 Q
b0 P
b11111111 A
b11111111 N
b11111111 ?
b1111111100000000 +
b1111111100000000 G
b0 H
b11111111 1
b11111111 =
b111 F
b111 O
b0 @
b0 M
b11111111 2
b11111111 :
b0 #
b0 <
b0 "
b0 9
b1111111 -
b111 /
b111 2"
0/"
10"
11"
b1111111 .
b111 0
b111 +"
0("
1)"
1*"
0-"
0."
0q
0&"
0'"
0Y
b1000 u
b1000 ]
b10000000 3
b10000000 o
b10000000 ,"
b0 r
0#"
1t
b1111111100000000 C
b1111111100000000 K
b10000000 4
b10000000 W
b10000000 %"
b0 Z
0i
1\
0|
0}
0~
b1000 s
0w
0x
0y
b1000 p
b10 n
b10 $"
b11111111 D
b11111111 I
b11111111 B
b11111111 L
0d
0e
0f
b1000 [
0_
0`
0a
b1000 X
b10 V
b10 j
b1000 !"
b10001000 m
b1000 z
b11 l
b11 ""
b11111111111 5
b11111111111 >
1!
b1000 g
b10001000 U
b1000 b
b11 T
b11 h
b1111 {
b1111 v
b1111 c
b1111 ^
b11111111 6
b11111111 ;
b11111111 k
b11111111 7
b11111111 8
b11111111 S
b11111111 '
b11111111 &
#100000
1("
b111000000000000 ,
b0 H
b1 #
b1 <
b111000000000000 *
b11 "
b11 9
b110 /
b110 2"
b100 0
b100 +"
b111 R
b1100 E
b1100 J
b1100 Q
b100 P
10"
01"
b111000000000000 +
b111000000000000 G
b1110000 ?
0)"
0*"
1f
b11 F
b11 O
b100 @
b100 M
b1000000 3
b1000000 o
b1000000 ,"
b100 u
b111000000000000 C
b111000000000000 K
b1000 A
b1000 N
1e
b10000 4
b10000 W
b10000 %"
b1 ]
1|
b100 s
1w
b100 p
b10000111 D
b10000111 I
b10000111 B
b10000111 L
1d
b1 [
b1100001 -
b100 !"
b1000100 m
b100 z
b10110000111 5
b10110000111 >
b1001110 .
b11000 U
b1 g
b10001000 1
b10001000 =
b100 {
b100 v
b11110000 2
b11110000 :
b1 c
b1110 ^
b1000100 6
b1000100 ;
b1000100 k
b11110 7
b11110 8
b11110 S
b1000100 '
b11110 &
