ILM/NOD/NOD.v


module NOD (
    input [7:0] A,
    output [7:0] O
);

    wire [5:0]t;
    wire [6:0] invert;
    wire [3:0] temp1;
    wire [3:0] temp2;
    wire [3:0] temp3;

    wire inter1;
    assign inter1 = A[6] && A[5];
    assign O[7] = A[7] || inter1;

    
    assign t[0] = ~A[7];
    wire not_a5;
    assign not_a5 = ~A[5];
    wire inter2;
    assign inter2 = A[6] && not_a5;
    wire not_a6;
    assign not_a6 = ~A[6];
    wire inter3;
    assign inter3 = A[5] && not_a6 && A[4];
    wire inter4;
    assign inter4 = inter2 || inter3;
    assign O[6] = t[0] && inter4;

    genvar i;
    generate
        
        for(i=5; i>1; i=i-1)
        begin
            

            assign invert[i+1] = ~A[i+1];
            assign invert[i] = ~A[i];
            assign invert[i-1] = ~A[i-1];
            assign t[6-i] = t[5-i] && invert[i+1];
            assign temp1[5-i] = A[i] && invert[i-1];
            assign temp2[5-i] = A[i-1] && invert[i] && A[i-2];
            assign temp3[5-i] = temp1[5-i] || temp2[5-i];
            assign O[i] = t[6-i] && temp3[5-i];

        end 


    endgenerate

    assign t[5] = t[4] && invert[2];
    assign invert[0] = ~A[0];
    wire inter5;
    assign inter5 = A[1] && invert[0];
    assign O[1] = t[5] && inter5;

    assign O[0] = t[5] && invert[1] && A[0];


    
endmodule

ILM/NOD/NOD_tb.v
`timescale 1ns / 1ps

module NOD_tb;
    
    reg [7:0] A;
    wire [7:0] O;
    
    // Instantiate the NOD module
    NOD uut (
        .A(A),
        .O(O)
    );
    
    initial begin
        // Dump waves for GTKWave
        $dumpfile("nod_tb.vcd");
        $dumpvars(0, NOD_tb);
        
        // Monitor signals
        $monitor("Time=%0t A=%d O=%d", $time, A, O);
        
        // Apply test vectors
        A = 8'b00000000; #10; // Test case 1: All zeros
        A = 8'b00000001; #10; // Test case 2: Single 1 at LSB
        A = 8'b00000010; #10; // Test case 3: Single 1 at bit 1
        A = 8'b00000111; #10; // Test case 4: First three bits high
        A = 8'b01101100; #10; // Test case 5: Random middle bits
        A = 8'b10101010; #10; // Test case 6: Alternating bits
        A = 8'b11111111; #10; // Test case 7: All ones
        A = 8'b10000000; #10;
        A = 8'd73; #10 // Test case 8: Single 1 at MSB
        
        // End simulation
        $finish;
    end
    
endmodule

ILM/NOD/nod_tb.vcd
$date
	Sun Mar  9 12:21:12 2025
$end
$version
	Icarus Verilog
$end
$timescale
	1ps
$end
$scope module NOD_tb $end
$var wire 8 ! O [7:0] $end
$var reg 8 " A [7:0] $end
$scope module uut $end
$var wire 8 # A [7:0] $end
$var wire 1 $ inter1 $end
$var wire 1 % inter2 $end
$var wire 1 & inter3 $end
$var wire 1 ' inter4 $end
$var wire 1 ( inter5 $end
$var wire 7 ) invert [6:0] $end
$var wire 1 * not_a5 $end
$var wire 1 + not_a6 $end
$var wire 4 , temp3 [3:0] $end
$var wire 4 - temp2 [3:0] $end
$var wire 4 . temp1 [3:0] $end
$var wire 6 / t [5:0] $end
$var wire 8 0 O [7:0] $end
$scope begin genblk1[2] $end
$var parameter 3 1 i $end
$upscope $end
$scope begin genblk1[3] $end
$var parameter 3 2 i $end
$upscope $end
$scope begin genblk1[4] $end
$var parameter 4 3 i $end
$upscope $end
$scope begin genblk1[5] $end
$var parameter 4 4 i $end
$upscope $end
$upscope $end
$upscope $end
$enddefinitions $end
$comment Show the parameter values. $end
$dumpall
b101 4
b100 3
b11 2
b10 1
$end
#0
$dumpvars
b0 0
b111111 /
b0 .
b0 -
b0 ,
1+
1*
b1111111 )
0(
0'
0&
0%
0$
b0 #
b0 "
b0 !
$end
#10000
b1111110 )
b1 !
b1 0
b1 "
b1 #
#20000
1(
b1111101 )
b10 !
b10 0
b10 "
b10 #
#30000
b1000 !
b1000 0
b11111 /
b100 ,
0(
b100 -
b1111000 )
b111 "
b111 #
#40000
b1011 ,
b1 /
b10000000 !
b10000000 0
0'
b1001 .
b10 -
1$
0*
0%
0+
b10011 )
b1101100 "
b1101100 #
#50000
b101 ,
b0 -
b1010101 )
b101 .
0$
b0 /
1+
1(
b10101010 "
b10101010 #
#60000
b0 .
b0 ,
0(
0'
b0 -
1$
0+
0&
b0 )
b11111111 "
b11111111 #
#70000
0$
1*
1+
b1111111 )
b10000000 "
b10000000 #
#80000
b100 ,
1'
b100 .
b1000000 !
b1000000 0
b1 /
1%
0+
b110110 )
b1001001 "
b1001001 #
